{
  "Maui": [
    {
      "segment_number": 0,
      "start_frame": 0,
      "end_frame": 31,
      "start": 0.0,
      "end": 16.0,
      "duration": 16.0,
      "original_video": "kNnH8xvg5Gs",
      "original_segment_number": 0
    },
    {
      "segment_number": 1,
      "start_frame": 32,
      "end_frame": 39,
      "start": 16.0,
      "end": 20.0,
      "duration": 4.0,
      "original_video": "kNnH8xvg5Gs",
      "original_segment_number": 1
    },
    {
      "segment_number": 2,
      "start_frame": 40,
      "end_frame": 56,
      "start": 20.0,
      "end": 28.5,
      "duration": 8.5,
      "original_video": "kNnH8xvg5Gs",
      "original_segment_number": 2
    },
    {
      "segment_number": 3,
      "start_frame": 57,
      "end_frame": 94,
      "start": 28.5,
      "end": 47.5,
      "duration": 19.0,
      "original_video": "kNnH8xvg5Gs",
      "original_segment_number": 3
    },
    {
      "segment_number": 4,
      "start_frame": 95,
      "end_frame": 126,
      "start": 47.5,
      "end": 63.5,
      "duration": 16.0,
      "original_video": "kNnH8xvg5Gs",
      "original_segment_number": 4
    },
    {
      "segment_number": 5,
      "start_frame": 127,
      "end_frame": 138,
      "start": 63.5,
      "end": 69.5,
      "duration": 6.0,
      "original_video": "kNnH8xvg5Gs",
      "original_segment_number": 5
    },
    {
      "segment_number": 6,
      "start_frame": 139,
      "end_frame": 152,
      "start": 69.5,
      "end": 76.5,
      "duration": 7.0,
      "original_video": "kNnH8xvg5Gs",
      "original_segment_number": 6
    },
    {
      "segment_number": 7,
      "start_frame": 153,
      "end_frame": 178,
      "start": 76.5,
      "end": 89.5,
      "duration": 13.0,
      "original_video": "kNnH8xvg5Gs",
      "original_segment_number": 7
    },
    {
      "segment_number": 8,
      "start_frame": 179,
      "end_frame": 187,
      "start": 89.5,
      "end": 94.0,
      "duration": 4.5,
      "original_video": "kNnH8xvg5Gs",
      "original_segment_number": 8
    },
    {
      "segment_number": 9,
      "start_frame": 188,
      "end_frame": 196,
      "start": 94.0,
      "end": 98.5,
      "duration": 4.5,
      "original_video": "kNnH8xvg5Gs",
      "original_segment_number": 9
    },
    {
      "segment_number": 10,
      "start_frame": 197,
      "end_frame": 204,
      "start": 98.5,
      "end": 102.5,
      "duration": 4.0,
      "original_video": "kNnH8xvg5Gs",
      "original_segment_number": 10
    },
    {
      "segment_number": 11,
      "start_frame": 205,
      "end_frame": 230,
      "start": 102.5,
      "end": 115.5,
      "duration": 13.0,
      "original_video": "kNnH8xvg5Gs",
      "original_segment_number": 11
    },
    {
      "segment_number": 12,
      "start_frame": 231,
      "end_frame": 239,
      "start": 115.5,
      "end": 120.0,
      "duration": 4.5,
      "original_video": "kNnH8xvg5Gs",
      "original_segment_number": 12
    },
    {
      "segment_number": 13,
      "start_frame": 240,
      "end_frame": 254,
      "start": 120.0,
      "end": 127.5,
      "duration": 7.5,
      "original_video": "kNnH8xvg5Gs",
      "original_segment_number": 13
    },
    {
      "segment_number": 14,
      "start_frame": 255,
      "end_frame": 263,
      "start": 127.5,
      "end": 132.0,
      "duration": 4.5,
      "original_video": "kNnH8xvg5Gs",
      "original_segment_number": 14
    },
    {
      "segment_number": 15,
      "start_frame": 264,
      "end_frame": 300,
      "start": 132.0,
      "end": 150.5,
      "duration": 18.5,
      "original_video": "kNnH8xvg5Gs",
      "original_segment_number": 15
    },
    {
      "segment_number": 16,
      "start_frame": 301,
      "end_frame": 317,
      "start": 150.5,
      "end": 159.0,
      "duration": 8.5,
      "original_video": "kNnH8xvg5Gs",
      "original_segment_number": 16
    },
    {
      "segment_number": 17,
      "start_frame": 318,
      "end_frame": 326,
      "start": 159.0,
      "end": 163.5,
      "duration": 4.5,
      "original_video": "kNnH8xvg5Gs",
      "original_segment_number": 17
    },
    {
      "segment_number": 18,
      "start_frame": 327,
      "end_frame": 334,
      "start": 163.5,
      "end": 167.5,
      "duration": 4.0,
      "original_video": "kNnH8xvg5Gs",
      "original_segment_number": 18
    },
    {
      "segment_number": 19,
      "start_frame": 335,
      "end_frame": 342,
      "start": 167.5,
      "end": 171.5,
      "duration": 4.0,
      "original_video": "kNnH8xvg5Gs",
      "original_segment_number": 19
    },
    {
      "segment_number": 20,
      "start_frame": 343,
      "end_frame": 357,
      "start": 171.5,
      "end": 179.0,
      "duration": 7.5,
      "original_video": "kNnH8xvg5Gs",
      "original_segment_number": 20
    },
    {
      "segment_number": 21,
      "start_frame": 358,
      "end_frame": 374,
      "start": 179.0,
      "end": 187.5,
      "duration": 8.5,
      "original_video": "kNnH8xvg5Gs",
      "original_segment_number": 21
    },
    {
      "segment_number": 22,
      "start_frame": 375,
      "end_frame": 403,
      "start": 187.5,
      "end": 202.0,
      "duration": 14.5,
      "original_video": "kNnH8xvg5Gs",
      "original_segment_number": 22
    },
    {
      "segment_number": 23,
      "start_frame": 404,
      "end_frame": 411,
      "start": 202.0,
      "end": 206.0,
      "duration": 4.0,
      "original_video": "kNnH8xvg5Gs",
      "original_segment_number": 23
    },
    {
      "segment_number": 24,
      "start_frame": 412,
      "end_frame": 419,
      "start": 206.0,
      "end": 210.0,
      "duration": 4.0,
      "original_video": "kNnH8xvg5Gs",
      "original_segment_number": 24
    },
    {
      "segment_number": 25,
      "start_frame": 420,
      "end_frame": 460,
      "start": 210.0,
      "end": 230.5,
      "duration": 20.5,
      "original_video": "kNnH8xvg5Gs",
      "original_segment_number": 25
    },
    {
      "segment_number": 26,
      "start_frame": 461,
      "end_frame": 512,
      "start": 230.5,
      "end": 256.5,
      "duration": 26.0,
      "original_video": "kNnH8xvg5Gs",
      "original_segment_number": 26
    },
    {
      "segment_number": 27,
      "start_frame": 513,
      "end_frame": 521,
      "start": 256.5,
      "end": 261.0,
      "duration": 4.5,
      "original_video": "kNnH8xvg5Gs",
      "original_segment_number": 27
    },
    {
      "segment_number": 28,
      "start_frame": 522,
      "end_frame": 590,
      "start": 261.0,
      "end": 295.5,
      "duration": 34.5,
      "original_video": "kNnH8xvg5Gs",
      "original_segment_number": 28
    },
    {
      "segment_number": 29,
      "start_frame": 591,
      "end_frame": 651,
      "start": 295.5,
      "end": 326.0,
      "duration": 30.5,
      "original_video": "kNnH8xvg5Gs",
      "original_segment_number": 29
    },
    {
      "segment_number": 30,
      "start_frame": 652,
      "end_frame": 677,
      "start": 326.0,
      "end": 339.0,
      "duration": 13.0,
      "original_video": "kNnH8xvg5Gs",
      "original_segment_number": 30
    },
    {
      "segment_number": 31,
      "start_frame": 678,
      "end_frame": 701,
      "start": 339.0,
      "end": 351.0,
      "duration": 12.0,
      "original_video": "kNnH8xvg5Gs",
      "original_segment_number": 31
    },
    {
      "segment_number": 32,
      "start_frame": 702,
      "end_frame": 748,
      "start": 351.0,
      "end": 374.5,
      "duration": 23.5,
      "original_video": "kNnH8xvg5Gs",
      "original_segment_number": 32
    },
    {
      "segment_number": 33,
      "start_frame": 749,
      "end_frame": 756,
      "start": 374.5,
      "end": 378.5,
      "duration": 4.0,
      "original_video": "kNnH8xvg5Gs",
      "original_segment_number": 33
    },
    {
      "segment_number": 34,
      "start_frame": 757,
      "end_frame": 767,
      "start": 378.5,
      "end": 384.0,
      "duration": 5.5,
      "original_video": "kNnH8xvg5Gs",
      "original_segment_number": 34
    },
    {
      "segment_number": 35,
      "start_frame": 768,
      "end_frame": 775,
      "start": 384.0,
      "end": 388.0,
      "duration": 4.0,
      "original_video": "kNnH8xvg5Gs",
      "original_segment_number": 35
    },
    {
      "segment_number": 36,
      "start_frame": 776,
      "end_frame": 809,
      "start": 388.0,
      "end": 405.0,
      "duration": 17.0,
      "original_video": "kNnH8xvg5Gs",
      "original_segment_number": 36
    },
    {
      "segment_number": 37,
      "start_frame": 810,
      "end_frame": 816,
      "start": 405.0,
      "end": 408.5,
      "duration": 3.5,
      "original_video": "kNnH8xvg5Gs",
      "original_segment_number": 37
    },
    {
      "segment_number": 38,
      "start_frame": 817,
      "end_frame": 824,
      "start": 408.5,
      "end": 412.5,
      "duration": 4.0,
      "original_video": "kNnH8xvg5Gs",
      "original_segment_number": 38
    },
    {
      "segment_number": 39,
      "start_frame": 825,
      "end_frame": 840,
      "start": 412.5,
      "end": 420.5,
      "duration": 8.0,
      "original_video": "kNnH8xvg5Gs",
      "original_segment_number": 39
    },
    {
      "segment_number": 40,
      "start_frame": 841,
      "end_frame": 849,
      "start": 420.5,
      "end": 425.0,
      "duration": 4.5,
      "original_video": "kNnH8xvg5Gs",
      "original_segment_number": 40
    },
    {
      "segment_number": 41,
      "start_frame": 850,
      "end_frame": 856,
      "start": 425.0,
      "end": 428.5,
      "duration": 3.5,
      "original_video": "kNnH8xvg5Gs",
      "original_segment_number": 41
    },
    {
      "segment_number": 42,
      "start_frame": 857,
      "end_frame": 878,
      "start": 428.5,
      "end": 439.5,
      "duration": 11.0,
      "original_video": "kNnH8xvg5Gs",
      "original_segment_number": 42
    },
    {
      "segment_number": 43,
      "start_frame": 879,
      "end_frame": 912,
      "start": 439.5,
      "end": 456.5,
      "duration": 17.0,
      "original_video": "kNnH8xvg5Gs",
      "original_segment_number": 43
    },
    {
      "segment_number": 44,
      "start_frame": 913,
      "end_frame": 920,
      "start": 456.5,
      "end": 460.5,
      "duration": 4.0,
      "original_video": "kNnH8xvg5Gs",
      "original_segment_number": 44
    },
    {
      "segment_number": 45,
      "start_frame": 921,
      "end_frame": 928,
      "start": 460.5,
      "end": 464.5,
      "duration": 4.0,
      "original_video": "kNnH8xvg5Gs",
      "original_segment_number": 45
    },
    {
      "segment_number": 46,
      "start_frame": 929,
      "end_frame": 936,
      "start": 464.5,
      "end": 468.5,
      "duration": 4.0,
      "original_video": "kNnH8xvg5Gs",
      "original_segment_number": 46
    },
    {
      "segment_number": 47,
      "start_frame": 937,
      "end_frame": 959,
      "start": 468.5,
      "end": 480.0,
      "duration": 11.5,
      "original_video": "kNnH8xvg5Gs",
      "original_segment_number": 47
    },
    {
      "segment_number": 48,
      "start_frame": 960,
      "end_frame": 987,
      "start": 480.0,
      "end": 494.0,
      "duration": 14.0,
      "original_video": "kNnH8xvg5Gs",
      "original_segment_number": 48
    },
    {
      "segment_number": 49,
      "start_frame": 988,
      "end_frame": 995,
      "start": 494.0,
      "end": 498.0,
      "duration": 4.0,
      "original_video": "kNnH8xvg5Gs",
      "original_segment_number": 49
    },
    {
      "segment_number": 50,
      "start_frame": 996,
      "end_frame": 1003,
      "start": 498.0,
      "end": 502.0,
      "duration": 4.0,
      "original_video": "kNnH8xvg5Gs",
      "original_segment_number": 50
    },
    {
      "segment_number": 51,
      "start_frame": 1004,
      "end_frame": 1071,
      "start": 502.0,
      "end": 536.0,
      "duration": 34.0,
      "original_video": "kNnH8xvg5Gs",
      "original_segment_number": 51
    },
    {
      "segment_number": 52,
      "start_frame": 1072,
      "end_frame": 1107,
      "start": 536.0,
      "end": 554.0,
      "duration": 18.0,
      "original_video": "kNnH8xvg5Gs",
      "original_segment_number": 52
    },
    {
      "segment_number": 53,
      "start_frame": 1108,
      "end_frame": 1135,
      "start": 554.0,
      "end": 568.0,
      "duration": 14.0,
      "original_video": "kNnH8xvg5Gs",
      "original_segment_number": 53
    },
    {
      "segment_number": 54,
      "start_frame": 1136,
      "end_frame": 1152,
      "start": 568.0,
      "end": 576.5,
      "duration": 8.5,
      "original_video": "kNnH8xvg5Gs",
      "original_segment_number": 54
    },
    {
      "segment_number": 55,
      "start_frame": 1153,
      "end_frame": 1160,
      "start": 576.5,
      "end": 580.5,
      "duration": 4.0,
      "original_video": "kNnH8xvg5Gs",
      "original_segment_number": 55
    },
    {
      "segment_number": 56,
      "start_frame": 1161,
      "end_frame": 1168,
      "start": 580.5,
      "end": 584.5,
      "duration": 4.0,
      "original_video": "kNnH8xvg5Gs",
      "original_segment_number": 56
    },
    {
      "segment_number": 57,
      "start_frame": 1169,
      "end_frame": 1191,
      "start": 584.5,
      "end": 596.0,
      "duration": 11.5,
      "original_video": "kNnH8xvg5Gs",
      "original_segment_number": 57
    },
    {
      "segment_number": 58,
      "start_frame": 1192,
      "end_frame": 1218,
      "start": 596.0,
      "end": 609.5,
      "duration": 13.5,
      "original_video": "kNnH8xvg5Gs",
      "original_segment_number": 58
    },
    {
      "segment_number": 59,
      "start_frame": 1219,
      "end_frame": 1227,
      "start": 609.5,
      "end": 614.0,
      "duration": 4.5,
      "original_video": "kNnH8xvg5Gs",
      "original_segment_number": 59
    },
    {
      "segment_number": 60,
      "start_frame": 1228,
      "end_frame": 1251,
      "start": 614.0,
      "end": 626.0,
      "duration": 12.0,
      "original_video": "kNnH8xvg5Gs",
      "original_segment_number": 60
    },
    {
      "segment_number": 61,
      "start_frame": 1252,
      "end_frame": 1260,
      "start": 626.0,
      "end": 630.5,
      "duration": 4.5,
      "original_video": "kNnH8xvg5Gs",
      "original_segment_number": 61
    },
    {
      "segment_number": 62,
      "start_frame": 1261,
      "end_frame": 1270,
      "start": 630.5,
      "end": 635.5,
      "duration": 5.0,
      "original_video": "kNnH8xvg5Gs",
      "original_segment_number": 62
    },
    {
      "segment_number": 63,
      "start_frame": 1271,
      "end_frame": 1285,
      "start": 635.5,
      "end": 643.0,
      "duration": 7.5,
      "original_video": "kNnH8xvg5Gs",
      "original_segment_number": 63
    },
    {
      "segment_number": 64,
      "start_frame": 1286,
      "end_frame": 1296,
      "start": 643.0,
      "end": 648.5,
      "duration": 5.5,
      "original_video": "kNnH8xvg5Gs",
      "original_segment_number": 64
    },
    {
      "segment_number": 65,
      "start_frame": 1297,
      "end_frame": 1305,
      "start": 648.5,
      "end": 653.0,
      "duration": 4.5,
      "original_video": "kNnH8xvg5Gs",
      "original_segment_number": 65
    },
    {
      "segment_number": 66,
      "start_frame": 1306,
      "end_frame": 1348,
      "start": 653.0,
      "end": 674.5,
      "duration": 21.5,
      "original_video": "kNnH8xvg5Gs",
      "original_segment_number": 66
    },
    {
      "segment_number": 67,
      "start_frame": 1349,
      "end_frame": 1356,
      "start": 674.5,
      "end": 678.5,
      "duration": 4.0,
      "original_video": "kNnH8xvg5Gs",
      "original_segment_number": 67
    },
    {
      "segment_number": 68,
      "start_frame": 1357,
      "end_frame": 1386,
      "start": 678.5,
      "end": 693.5,
      "duration": 15.0,
      "original_video": "kNnH8xvg5Gs",
      "original_segment_number": 68
    },
    {
      "segment_number": 69,
      "start_frame": 1387,
      "end_frame": 1405,
      "start": 693.5,
      "end": 703.0,
      "duration": 9.5,
      "original_video": "kNnH8xvg5Gs",
      "original_segment_number": 69
    },
    {
      "segment_number": 70,
      "start_frame": 1406,
      "end_frame": 1413,
      "start": 703.0,
      "end": 707.0,
      "duration": 4.0,
      "original_video": "LoHOe4lpPDw",
      "original_segment_number": 0
    },
    {
      "segment_number": 71,
      "start_frame": 1414,
      "end_frame": 1433,
      "start": 707.0,
      "end": 717.0,
      "duration": 10.0,
      "original_video": "LoHOe4lpPDw",
      "original_segment_number": 1
    },
    {
      "segment_number": 72,
      "start_frame": 1434,
      "end_frame": 1487,
      "start": 717.0,
      "end": 744.0,
      "duration": 27.0,
      "original_video": "LoHOe4lpPDw",
      "original_segment_number": 2
    },
    {
      "segment_number": 73,
      "start_frame": 1488,
      "end_frame": 1494,
      "start": 744.0,
      "end": 747.5,
      "duration": 3.5,
      "original_video": "LoHOe4lpPDw",
      "original_segment_number": 3
    },
    {
      "segment_number": 74,
      "start_frame": 1495,
      "end_frame": 1500,
      "start": 747.5,
      "end": 750.5,
      "duration": 3.0,
      "original_video": "LoHOe4lpPDw",
      "original_segment_number": 4
    },
    {
      "segment_number": 75,
      "start_frame": 1501,
      "end_frame": 1517,
      "start": 750.5,
      "end": 759.0,
      "duration": 8.5,
      "original_video": "LoHOe4lpPDw",
      "original_segment_number": 5
    },
    {
      "segment_number": 76,
      "start_frame": 1518,
      "end_frame": 1587,
      "start": 759.0,
      "end": 794.0,
      "duration": 35.0,
      "original_video": "LoHOe4lpPDw",
      "original_segment_number": 6
    },
    {
      "segment_number": 77,
      "start_frame": 1588,
      "end_frame": 1620,
      "start": 794.0,
      "end": 810.5,
      "duration": 16.5,
      "original_video": "LoHOe4lpPDw",
      "original_segment_number": 7
    },
    {
      "segment_number": 78,
      "start_frame": 1621,
      "end_frame": 1636,
      "start": 810.5,
      "end": 818.5,
      "duration": 8.0,
      "original_video": "LoHOe4lpPDw",
      "original_segment_number": 8
    },
    {
      "segment_number": 79,
      "start_frame": 1637,
      "end_frame": 1676,
      "start": 818.5,
      "end": 838.5,
      "duration": 20.0,
      "original_video": "LoHOe4lpPDw",
      "original_segment_number": 9
    },
    {
      "segment_number": 80,
      "start_frame": 1677,
      "end_frame": 1702,
      "start": 838.5,
      "end": 851.5,
      "duration": 13.0,
      "original_video": "LoHOe4lpPDw",
      "original_segment_number": 10
    },
    {
      "segment_number": 81,
      "start_frame": 1703,
      "end_frame": 1712,
      "start": 851.5,
      "end": 856.5,
      "duration": 5.0,
      "original_video": "LoHOe4lpPDw",
      "original_segment_number": 11
    },
    {
      "segment_number": 82,
      "start_frame": 1713,
      "end_frame": 1716,
      "start": 856.5,
      "end": 858.5,
      "duration": 2.0,
      "original_video": "LoHOe4lpPDw",
      "original_segment_number": 12
    },
    {
      "segment_number": 83,
      "start_frame": 1717,
      "end_frame": 1723,
      "start": 858.5,
      "end": 862.0,
      "duration": 3.5,
      "original_video": "LoHOe4lpPDw",
      "original_segment_number": 13
    },
    {
      "segment_number": 84,
      "start_frame": 1724,
      "end_frame": 1730,
      "start": 862.0,
      "end": 865.5,
      "duration": 3.5,
      "original_video": "LoHOe4lpPDw",
      "original_segment_number": 14
    },
    {
      "segment_number": 85,
      "start_frame": 1731,
      "end_frame": 1735,
      "start": 865.5,
      "end": 868.0,
      "duration": 2.5,
      "original_video": "LoHOe4lpPDw",
      "original_segment_number": 15
    },
    {
      "segment_number": 86,
      "start_frame": 1736,
      "end_frame": 1742,
      "start": 868.0,
      "end": 871.5,
      "duration": 3.5,
      "original_video": "LoHOe4lpPDw",
      "original_segment_number": 16
    },
    {
      "segment_number": 87,
      "start_frame": 1743,
      "end_frame": 1755,
      "start": 871.5,
      "end": 878.0,
      "duration": 6.5,
      "original_video": "LoHOe4lpPDw",
      "original_segment_number": 17
    },
    {
      "segment_number": 88,
      "start_frame": 1756,
      "end_frame": 1765,
      "start": 878.0,
      "end": 883.0,
      "duration": 5.0,
      "original_video": "LoHOe4lpPDw",
      "original_segment_number": 18
    },
    {
      "segment_number": 89,
      "start_frame": 1766,
      "end_frame": 1772,
      "start": 883.0,
      "end": 886.5,
      "duration": 3.5,
      "original_video": "LoHOe4lpPDw",
      "original_segment_number": 19
    },
    {
      "segment_number": 90,
      "start_frame": 1773,
      "end_frame": 1791,
      "start": 886.5,
      "end": 896.0,
      "duration": 9.5,
      "original_video": "LoHOe4lpPDw",
      "original_segment_number": 20
    },
    {
      "segment_number": 91,
      "start_frame": 1792,
      "end_frame": 1795,
      "start": 896.0,
      "end": 898.0,
      "duration": 2.0,
      "original_video": "LoHOe4lpPDw",
      "original_segment_number": 21
    },
    {
      "segment_number": 92,
      "start_frame": 1796,
      "end_frame": 1813,
      "start": 898.0,
      "end": 907.0,
      "duration": 9.0,
      "original_video": "LoHOe4lpPDw",
      "original_segment_number": 22
    },
    {
      "segment_number": 93,
      "start_frame": 1814,
      "end_frame": 1819,
      "start": 907.0,
      "end": 910.0,
      "duration": 3.0,
      "original_video": "LoHOe4lpPDw",
      "original_segment_number": 23
    },
    {
      "segment_number": 94,
      "start_frame": 1820,
      "end_frame": 1827,
      "start": 910.0,
      "end": 914.0,
      "duration": 4.0,
      "original_video": "LoHOe4lpPDw",
      "original_segment_number": 24
    },
    {
      "segment_number": 95,
      "start_frame": 1828,
      "end_frame": 1844,
      "start": 914.0,
      "end": 922.5,
      "duration": 8.5,
      "original_video": "LoHOe4lpPDw",
      "original_segment_number": 25
    },
    {
      "segment_number": 96,
      "start_frame": 1845,
      "end_frame": 1855,
      "start": 922.5,
      "end": 928.0,
      "duration": 5.5,
      "original_video": "LoHOe4lpPDw",
      "original_segment_number": 26
    },
    {
      "segment_number": 97,
      "start_frame": 1856,
      "end_frame": 1859,
      "start": 928.0,
      "end": 930.0,
      "duration": 2.0,
      "original_video": "LoHOe4lpPDw",
      "original_segment_number": 27
    },
    {
      "segment_number": 98,
      "start_frame": 1860,
      "end_frame": 1878,
      "start": 930.0,
      "end": 939.5,
      "duration": 9.5,
      "original_video": "LoHOe4lpPDw",
      "original_segment_number": 28
    },
    {
      "segment_number": 99,
      "start_frame": 1879,
      "end_frame": 1888,
      "start": 939.5,
      "end": 944.5,
      "duration": 5.0,
      "original_video": "LoHOe4lpPDw",
      "original_segment_number": 29
    },
    {
      "segment_number": 100,
      "start_frame": 1889,
      "end_frame": 1925,
      "start": 944.5,
      "end": 963.0,
      "duration": 18.5,
      "original_video": "LoHOe4lpPDw",
      "original_segment_number": 30
    },
    {
      "segment_number": 101,
      "start_frame": 1926,
      "end_frame": 1954,
      "start": 963.0,
      "end": 977.5,
      "duration": 14.5,
      "original_video": "LoHOe4lpPDw",
      "original_segment_number": 31
    },
    {
      "segment_number": 102,
      "start_frame": 1955,
      "end_frame": 2010,
      "start": 977.5,
      "end": 1005.5,
      "duration": 28.0,
      "original_video": "LoHOe4lpPDw",
      "original_segment_number": 32
    },
    {
      "segment_number": 103,
      "start_frame": 2011,
      "end_frame": 2033,
      "start": 1005.5,
      "end": 1017.0,
      "duration": 11.5,
      "original_video": "LoHOe4lpPDw",
      "original_segment_number": 33
    },
    {
      "segment_number": 104,
      "start_frame": 2034,
      "end_frame": 2067,
      "start": 1017.0,
      "end": 1034.0,
      "duration": 17.0,
      "original_video": "LoHOe4lpPDw",
      "original_segment_number": 34
    },
    {
      "segment_number": 105,
      "start_frame": 2068,
      "end_frame": 2083,
      "start": 1034.0,
      "end": 1042.0,
      "duration": 8.0,
      "original_video": "LoHOe4lpPDw",
      "original_segment_number": 35
    },
    {
      "segment_number": 106,
      "start_frame": 2084,
      "end_frame": 2114,
      "start": 1042.0,
      "end": 1057.5,
      "duration": 15.5,
      "original_video": "LoHOe4lpPDw",
      "original_segment_number": 36
    },
    {
      "segment_number": 107,
      "start_frame": 2115,
      "end_frame": 2122,
      "start": 1057.5,
      "end": 1061.5,
      "duration": 4.0,
      "original_video": "LoHOe4lpPDw",
      "original_segment_number": 37
    },
    {
      "segment_number": 108,
      "start_frame": 2123,
      "end_frame": 2155,
      "start": 1061.5,
      "end": 1078.0,
      "duration": 16.5,
      "original_video": "LoHOe4lpPDw",
      "original_segment_number": 38
    },
    {
      "segment_number": 109,
      "start_frame": 2156,
      "end_frame": 2167,
      "start": 1078.0,
      "end": 1084.0,
      "duration": 6.0,
      "original_video": "LoHOe4lpPDw",
      "original_segment_number": 39
    },
    {
      "segment_number": 110,
      "start_frame": 2168,
      "end_frame": 2185,
      "start": 1084.0,
      "end": 1093.0,
      "duration": 9.0,
      "original_video": "LoHOe4lpPDw",
      "original_segment_number": 40
    },
    {
      "segment_number": 111,
      "start_frame": 2186,
      "end_frame": 2197,
      "start": 1093.0,
      "end": 1099.0,
      "duration": 6.0,
      "original_video": "LoHOe4lpPDw",
      "original_segment_number": 41
    },
    {
      "segment_number": 112,
      "start_frame": 2198,
      "end_frame": 2227,
      "start": 1099.0,
      "end": 1114.0,
      "duration": 15.0,
      "original_video": "LoHOe4lpPDw",
      "original_segment_number": 42
    },
    {
      "segment_number": 113,
      "start_frame": 2228,
      "end_frame": 2234,
      "start": 1114.0,
      "end": 1117.5,
      "duration": 3.5,
      "original_video": "LoHOe4lpPDw",
      "original_segment_number": 43
    },
    {
      "segment_number": 114,
      "start_frame": 2235,
      "end_frame": 2251,
      "start": 1117.5,
      "end": 1126.0,
      "duration": 8.5,
      "original_video": "LoHOe4lpPDw",
      "original_segment_number": 44
    },
    {
      "segment_number": 115,
      "start_frame": 2252,
      "end_frame": 2272,
      "start": 1126.0,
      "end": 1136.5,
      "duration": 10.5,
      "original_video": "LoHOe4lpPDw",
      "original_segment_number": 45
    },
    {
      "segment_number": 116,
      "start_frame": 2273,
      "end_frame": 2311,
      "start": 1136.5,
      "end": 1156.0,
      "duration": 19.5,
      "original_video": "LoHOe4lpPDw",
      "original_segment_number": 46
    },
    {
      "segment_number": 117,
      "start_frame": 2312,
      "end_frame": 2341,
      "start": 1156.0,
      "end": 1171.0,
      "duration": 15.0,
      "original_video": "LoHOe4lpPDw",
      "original_segment_number": 47
    },
    {
      "segment_number": 118,
      "start_frame": 2342,
      "end_frame": 2367,
      "start": 1171.0,
      "end": 1184.0,
      "duration": 13.0,
      "original_video": "LoHOe4lpPDw",
      "original_segment_number": 48
    },
    {
      "segment_number": 119,
      "start_frame": 2368,
      "end_frame": 2413,
      "start": 1184.0,
      "end": 1207.0,
      "duration": 23.0,
      "original_video": "LoHOe4lpPDw",
      "original_segment_number": 49
    },
    {
      "segment_number": 120,
      "start_frame": 2414,
      "end_frame": 2437,
      "start": 1207.0,
      "end": 1219.0,
      "duration": 12.0,
      "original_video": "LoHOe4lpPDw",
      "original_segment_number": 50
    },
    {
      "segment_number": 121,
      "start_frame": 2438,
      "end_frame": 2467,
      "start": 1219.0,
      "end": 1234.0,
      "duration": 15.0,
      "original_video": "LoHOe4lpPDw",
      "original_segment_number": 51
    },
    {
      "segment_number": 122,
      "start_frame": 2468,
      "end_frame": 2513,
      "start": 1234.0,
      "end": 1257.0,
      "duration": 23.0,
      "original_video": "LoHOe4lpPDw",
      "original_segment_number": 52
    },
    {
      "segment_number": 123,
      "start_frame": 2514,
      "end_frame": 2535,
      "start": 1257.0,
      "end": 1268.0,
      "duration": 11.0,
      "original_video": "LoHOe4lpPDw",
      "original_segment_number": 53
    },
    {
      "segment_number": 124,
      "start_frame": 2536,
      "end_frame": 2552,
      "start": 1268.0,
      "end": 1276.5,
      "duration": 8.5,
      "original_video": "LoHOe4lpPDw",
      "original_segment_number": 54
    },
    {
      "segment_number": 125,
      "start_frame": 2553,
      "end_frame": 2560,
      "start": 1276.5,
      "end": 1280.5,
      "duration": 4.0,
      "original_video": "LoHOe4lpPDw",
      "original_segment_number": 55
    },
    {
      "segment_number": 126,
      "start_frame": 2561,
      "end_frame": 2571,
      "start": 1280.5,
      "end": 1286.0,
      "duration": 5.5,
      "original_video": "LoHOe4lpPDw",
      "original_segment_number": 56
    },
    {
      "segment_number": 127,
      "start_frame": 2572,
      "end_frame": 2585,
      "start": 1286.0,
      "end": 1293.0,
      "duration": 7.0,
      "original_video": "LoHOe4lpPDw",
      "original_segment_number": 57
    },
    {
      "segment_number": 128,
      "start_frame": 2586,
      "end_frame": 2611,
      "start": 1293.0,
      "end": 1306.0,
      "duration": 13.0,
      "original_video": "LoHOe4lpPDw",
      "original_segment_number": 58
    },
    {
      "segment_number": 129,
      "start_frame": 2612,
      "end_frame": 2620,
      "start": 1306.0,
      "end": 1310.5,
      "duration": 4.5,
      "original_video": "LoHOe4lpPDw",
      "original_segment_number": 59
    },
    {
      "segment_number": 130,
      "start_frame": 2621,
      "end_frame": 2670,
      "start": 1310.5,
      "end": 1335.5,
      "duration": 25.0,
      "original_video": "LoHOe4lpPDw",
      "original_segment_number": 60
    },
    {
      "segment_number": 131,
      "start_frame": 2671,
      "end_frame": 2677,
      "start": 1335.5,
      "end": 1339.0,
      "duration": 3.5,
      "original_video": "LoHOe4lpPDw",
      "original_segment_number": 61
    },
    {
      "segment_number": 132,
      "start_frame": 2678,
      "end_frame": 2691,
      "start": 1339.0,
      "end": 1346.0,
      "duration": 7.0,
      "original_video": "LoHOe4lpPDw",
      "original_segment_number": 62
    },
    {
      "segment_number": 133,
      "start_frame": 2692,
      "end_frame": 2707,
      "start": 1346.0,
      "end": 1354.0,
      "duration": 8.0,
      "original_video": "LoHOe4lpPDw",
      "original_segment_number": 63
    },
    {
      "segment_number": 134,
      "start_frame": 2708,
      "end_frame": 2713,
      "start": 1354.0,
      "end": 1357.0,
      "duration": 3.0,
      "original_video": "LoHOe4lpPDw",
      "original_segment_number": 64
    },
    {
      "segment_number": 135,
      "start_frame": 2714,
      "end_frame": 2787,
      "start": 1357.0,
      "end": 1394.0,
      "duration": 37.0,
      "original_video": "LoHOe4lpPDw",
      "original_segment_number": 65
    },
    {
      "segment_number": 136,
      "start_frame": 2788,
      "end_frame": 2815,
      "start": 1394.0,
      "end": 1408.0,
      "duration": 14.0,
      "original_video": "LoHOe4lpPDw",
      "original_segment_number": 66
    },
    {
      "segment_number": 137,
      "start_frame": 2816,
      "end_frame": 2841,
      "start": 1408.0,
      "end": 1421.0,
      "duration": 13.0,
      "original_video": "LoHOe4lpPDw",
      "original_segment_number": 67
    },
    {
      "segment_number": 138,
      "start_frame": 2842,
      "end_frame": 2885,
      "start": 1421.0,
      "end": 1443.0,
      "duration": 22.0,
      "original_video": "LoHOe4lpPDw",
      "original_segment_number": 68
    },
    {
      "segment_number": 139,
      "start_frame": 2886,
      "end_frame": 2904,
      "start": 1443.0,
      "end": 1452.5,
      "duration": 9.5,
      "original_video": "LoHOe4lpPDw",
      "original_segment_number": 69
    },
    {
      "segment_number": 140,
      "start_frame": 2905,
      "end_frame": 2924,
      "start": 1452.5,
      "end": 1462.5,
      "duration": 10.0,
      "original_video": "LoHOe4lpPDw",
      "original_segment_number": 70
    },
    {
      "segment_number": 141,
      "start_frame": 2925,
      "end_frame": 2937,
      "start": 1462.5,
      "end": 1469.0,
      "duration": 6.5,
      "original_video": "LoHOe4lpPDw",
      "original_segment_number": 71
    },
    {
      "segment_number": 142,
      "start_frame": 2938,
      "end_frame": 2967,
      "start": 1469.0,
      "end": 1484.0,
      "duration": 15.0,
      "original_video": "LoHOe4lpPDw",
      "original_segment_number": 72
    },
    {
      "segment_number": 143,
      "start_frame": 2968,
      "end_frame": 2993,
      "start": 1484.0,
      "end": 1497.0,
      "duration": 13.0,
      "original_video": "LoHOe4lpPDw",
      "original_segment_number": 73
    },
    {
      "segment_number": 144,
      "start_frame": 2994,
      "end_frame": 3029,
      "start": 1497.0,
      "end": 1515.0,
      "duration": 18.0,
      "original_video": "LoHOe4lpPDw",
      "original_segment_number": 74
    },
    {
      "segment_number": 145,
      "start_frame": 3030,
      "end_frame": 3054,
      "start": 1515.0,
      "end": 1527.5,
      "duration": 12.5,
      "original_video": "LoHOe4lpPDw",
      "original_segment_number": 75
    },
    {
      "segment_number": 146,
      "start_frame": 3055,
      "end_frame": 3095,
      "start": 1527.5,
      "end": 1548.0,
      "duration": 20.5,
      "original_video": "LoHOe4lpPDw",
      "original_segment_number": 76
    },
    {
      "segment_number": 147,
      "start_frame": 3096,
      "end_frame": 3110,
      "start": 1548.0,
      "end": 1555.5,
      "duration": 7.5,
      "original_video": "LoHOe4lpPDw",
      "original_segment_number": 77
    },
    {
      "segment_number": 148,
      "start_frame": 3111,
      "end_frame": 3122,
      "start": 1555.5,
      "end": 1561.5,
      "duration": 6.0,
      "original_video": "LoHOe4lpPDw",
      "original_segment_number": 78
    },
    {
      "segment_number": 149,
      "start_frame": 3123,
      "end_frame": 3135,
      "start": 1561.5,
      "end": 1568.0,
      "duration": 6.5,
      "original_video": "LoHOe4lpPDw",
      "original_segment_number": 79
    },
    {
      "segment_number": 150,
      "start_frame": 3136,
      "end_frame": 3142,
      "start": 1568.0,
      "end": 1571.5,
      "duration": 3.5,
      "original_video": "LoHOe4lpPDw",
      "original_segment_number": 80
    },
    {
      "segment_number": 151,
      "start_frame": 3143,
      "end_frame": 3148,
      "start": 1571.5,
      "end": 1574.5,
      "duration": 3.0,
      "original_video": "LoHOe4lpPDw",
      "original_segment_number": 81
    },
    {
      "segment_number": 152,
      "start_frame": 3149,
      "end_frame": 3164,
      "start": 1574.5,
      "end": 1582.5,
      "duration": 8.0,
      "original_video": "LoHOe4lpPDw",
      "original_segment_number": 82
    },
    {
      "segment_number": 153,
      "start_frame": 3165,
      "end_frame": 3192,
      "start": 1582.5,
      "end": 1596.5,
      "duration": 14.0,
      "original_video": "LoHOe4lpPDw",
      "original_segment_number": 83
    },
    {
      "segment_number": 154,
      "start_frame": 3193,
      "end_frame": 3215,
      "start": 1596.5,
      "end": 1608.0,
      "duration": 11.5,
      "original_video": "LoHOe4lpPDw",
      "original_segment_number": 84
    },
    {
      "segment_number": 155,
      "start_frame": 3216,
      "end_frame": 3230,
      "start": 1608.0,
      "end": 1615.5,
      "duration": 7.5,
      "original_video": "LoHOe4lpPDw",
      "original_segment_number": 85
    },
    {
      "segment_number": 156,
      "start_frame": 3231,
      "end_frame": 3240,
      "start": 1615.5,
      "end": 1620.5,
      "duration": 5.0,
      "original_video": "LoHOe4lpPDw",
      "original_segment_number": 86
    },
    {
      "segment_number": 157,
      "start_frame": 3241,
      "end_frame": 3263,
      "start": 1620.5,
      "end": 1632.0,
      "duration": 11.5,
      "original_video": "LoHOe4lpPDw",
      "original_segment_number": 87
    },
    {
      "segment_number": 158,
      "start_frame": 3264,
      "end_frame": 3276,
      "start": 1632.0,
      "end": 1638.5,
      "duration": 6.5,
      "original_video": "LoHOe4lpPDw",
      "original_segment_number": 88
    },
    {
      "segment_number": 159,
      "start_frame": 3277,
      "end_frame": 3286,
      "start": 1638.5,
      "end": 1643.5,
      "duration": 5.0,
      "original_video": "LoHOe4lpPDw",
      "original_segment_number": 89
    },
    {
      "segment_number": 160,
      "start_frame": 3287,
      "end_frame": 3315,
      "start": 1643.5,
      "end": 1658.0,
      "duration": 14.5,
      "original_video": "LoHOe4lpPDw",
      "original_segment_number": 90
    },
    {
      "segment_number": 161,
      "start_frame": 3316,
      "end_frame": 3338,
      "start": 1658.0,
      "end": 1669.5,
      "duration": 11.5,
      "original_video": "LoHOe4lpPDw",
      "original_segment_number": 91
    },
    {
      "segment_number": 162,
      "start_frame": 3339,
      "end_frame": 3362,
      "start": 1669.5,
      "end": 1681.5,
      "duration": 12.0,
      "original_video": "LoHOe4lpPDw",
      "original_segment_number": 92
    },
    {
      "segment_number": 163,
      "start_frame": 3363,
      "end_frame": 3381,
      "start": 1681.5,
      "end": 1691.0,
      "duration": 9.5,
      "original_video": "LoHOe4lpPDw",
      "original_segment_number": 93
    },
    {
      "segment_number": 164,
      "start_frame": 3382,
      "end_frame": 3394,
      "start": 1691.0,
      "end": 1697.5,
      "duration": 6.5,
      "original_video": "LoHOe4lpPDw",
      "original_segment_number": 94
    },
    {
      "segment_number": 165,
      "start_frame": 3395,
      "end_frame": 3399,
      "start": 1697.5,
      "end": 1700.0,
      "duration": 2.5,
      "original_video": "LoHOe4lpPDw",
      "original_segment_number": 95
    },
    {
      "segment_number": 166,
      "start_frame": 3400,
      "end_frame": 3421,
      "start": 1700.0,
      "end": 1711.0,
      "duration": 11.0,
      "original_video": "LoHOe4lpPDw",
      "original_segment_number": 96
    },
    {
      "segment_number": 167,
      "start_frame": 3422,
      "end_frame": 3428,
      "start": 1711.0,
      "end": 1714.5,
      "duration": 3.5,
      "original_video": "LoHOe4lpPDw",
      "original_segment_number": 97
    },
    {
      "segment_number": 168,
      "start_frame": 3429,
      "end_frame": 3435,
      "start": 1714.5,
      "end": 1718.0,
      "duration": 3.5,
      "original_video": "LoHOe4lpPDw",
      "original_segment_number": 98
    },
    {
      "segment_number": 169,
      "start_frame": 3436,
      "end_frame": 3450,
      "start": 1718.0,
      "end": 1725.5,
      "duration": 7.5,
      "original_video": "LoHOe4lpPDw",
      "original_segment_number": 99
    },
    {
      "segment_number": 170,
      "start_frame": 3451,
      "end_frame": 3458,
      "start": 1725.5,
      "end": 1729.5,
      "duration": 4.0,
      "original_video": "LoHOe4lpPDw",
      "original_segment_number": 100
    },
    {
      "segment_number": 171,
      "start_frame": 3459,
      "end_frame": 3465,
      "start": 1729.5,
      "end": 1733.0,
      "duration": 3.5,
      "original_video": "LoHOe4lpPDw",
      "original_segment_number": 101
    },
    {
      "segment_number": 172,
      "start_frame": 3466,
      "end_frame": 3469,
      "start": 1733.0,
      "end": 1735.0,
      "duration": 2.0,
      "original_video": "LoHOe4lpPDw",
      "original_segment_number": 102
    },
    {
      "segment_number": 173,
      "start_frame": 3470,
      "end_frame": 3473,
      "start": 1735.0,
      "end": 1737.0,
      "duration": 2.0,
      "original_video": "LoHOe4lpPDw",
      "original_segment_number": 103
    },
    {
      "segment_number": 174,
      "start_frame": 3474,
      "end_frame": 3498,
      "start": 1737.0,
      "end": 1749.5,
      "duration": 12.5,
      "original_video": "LoHOe4lpPDw",
      "original_segment_number": 104
    },
    {
      "segment_number": 175,
      "start_frame": 3499,
      "end_frame": 3517,
      "start": 1749.5,
      "end": 1759.0,
      "duration": 9.5,
      "original_video": "LoHOe4lpPDw",
      "original_segment_number": 105
    },
    {
      "segment_number": 176,
      "start_frame": 3518,
      "end_frame": 3557,
      "start": 1759.0,
      "end": 1779.0,
      "duration": 20.0,
      "original_video": "LoHOe4lpPDw",
      "original_segment_number": 106
    },
    {
      "segment_number": 177,
      "start_frame": 3558,
      "end_frame": 3594,
      "start": 1779.0,
      "end": 1797.5,
      "duration": 18.5,
      "original_video": "4TYdFNfMo8k",
      "original_segment_number": 0
    },
    {
      "segment_number": 178,
      "start_frame": 3595,
      "end_frame": 3615,
      "start": 1797.5,
      "end": 1808.0,
      "duration": 10.5,
      "original_video": "4TYdFNfMo8k",
      "original_segment_number": 1
    },
    {
      "segment_number": 179,
      "start_frame": 3616,
      "end_frame": 3641,
      "start": 1808.0,
      "end": 1821.0,
      "duration": 13.0,
      "original_video": "4TYdFNfMo8k",
      "original_segment_number": 2
    },
    {
      "segment_number": 180,
      "start_frame": 3642,
      "end_frame": 3646,
      "start": 1821.0,
      "end": 1823.5,
      "duration": 2.5,
      "original_video": "4TYdFNfMo8k",
      "original_segment_number": 3
    },
    {
      "segment_number": 181,
      "start_frame": 3647,
      "end_frame": 3651,
      "start": 1823.5,
      "end": 1826.0,
      "duration": 2.5,
      "original_video": "4TYdFNfMo8k",
      "original_segment_number": 4
    },
    {
      "segment_number": 182,
      "start_frame": 3652,
      "end_frame": 3663,
      "start": 1826.0,
      "end": 1832.0,
      "duration": 6.0,
      "original_video": "4TYdFNfMo8k",
      "original_segment_number": 5
    },
    {
      "segment_number": 183,
      "start_frame": 3664,
      "end_frame": 3710,
      "start": 1832.0,
      "end": 1855.5,
      "duration": 23.5,
      "original_video": "4TYdFNfMo8k",
      "original_segment_number": 6
    },
    {
      "segment_number": 184,
      "start_frame": 3711,
      "end_frame": 3738,
      "start": 1855.5,
      "end": 1869.5,
      "duration": 14.0,
      "original_video": "4TYdFNfMo8k",
      "original_segment_number": 7
    },
    {
      "segment_number": 185,
      "start_frame": 3739,
      "end_frame": 3769,
      "start": 1869.5,
      "end": 1885.0,
      "duration": 15.5,
      "original_video": "4TYdFNfMo8k",
      "original_segment_number": 8
    },
    {
      "segment_number": 186,
      "start_frame": 3770,
      "end_frame": 3776,
      "start": 1885.0,
      "end": 1888.5,
      "duration": 3.5,
      "original_video": "4TYdFNfMo8k",
      "original_segment_number": 9
    },
    {
      "segment_number": 187,
      "start_frame": 3777,
      "end_frame": 3783,
      "start": 1888.5,
      "end": 1892.0,
      "duration": 3.5,
      "original_video": "4TYdFNfMo8k",
      "original_segment_number": 10
    },
    {
      "segment_number": 188,
      "start_frame": 3784,
      "end_frame": 3795,
      "start": 1892.0,
      "end": 1898.0,
      "duration": 6.0,
      "original_video": "4TYdFNfMo8k",
      "original_segment_number": 11
    },
    {
      "segment_number": 189,
      "start_frame": 3796,
      "end_frame": 3850,
      "start": 1898.0,
      "end": 1925.5,
      "duration": 27.5,
      "original_video": "4TYdFNfMo8k",
      "original_segment_number": 12
    },
    {
      "segment_number": 190,
      "start_frame": 3851,
      "end_frame": 3866,
      "start": 1925.5,
      "end": 1933.5,
      "duration": 8.0,
      "original_video": "4TYdFNfMo8k",
      "original_segment_number": 13
    },
    {
      "segment_number": 191,
      "start_frame": 3867,
      "end_frame": 3875,
      "start": 1933.5,
      "end": 1938.0,
      "duration": 4.5,
      "original_video": "4TYdFNfMo8k",
      "original_segment_number": 14
    },
    {
      "segment_number": 192,
      "start_frame": 3876,
      "end_frame": 3890,
      "start": 1938.0,
      "end": 1945.5,
      "duration": 7.5,
      "original_video": "4TYdFNfMo8k",
      "original_segment_number": 15
    },
    {
      "segment_number": 193,
      "start_frame": 3891,
      "end_frame": 3923,
      "start": 1945.5,
      "end": 1962.0,
      "duration": 16.5,
      "original_video": "4TYdFNfMo8k",
      "original_segment_number": 16
    },
    {
      "segment_number": 194,
      "start_frame": 3924,
      "end_frame": 3942,
      "start": 1962.0,
      "end": 1971.5,
      "duration": 9.5,
      "original_video": "4TYdFNfMo8k",
      "original_segment_number": 17
    },
    {
      "segment_number": 195,
      "start_frame": 3943,
      "end_frame": 3957,
      "start": 1971.5,
      "end": 1979.0,
      "duration": 7.5,
      "original_video": "4TYdFNfMo8k",
      "original_segment_number": 18
    },
    {
      "segment_number": 196,
      "start_frame": 3958,
      "end_frame": 3966,
      "start": 1979.0,
      "end": 1983.5,
      "duration": 4.5,
      "original_video": "4TYdFNfMo8k",
      "original_segment_number": 19
    },
    {
      "segment_number": 197,
      "start_frame": 3967,
      "end_frame": 3998,
      "start": 1983.5,
      "end": 1999.5,
      "duration": 16.0,
      "original_video": "4TYdFNfMo8k",
      "original_segment_number": 20
    },
    {
      "segment_number": 198,
      "start_frame": 3999,
      "end_frame": 4014,
      "start": 1999.5,
      "end": 2007.5,
      "duration": 8.0,
      "original_video": "4TYdFNfMo8k",
      "original_segment_number": 21
    },
    {
      "segment_number": 199,
      "start_frame": 4015,
      "end_frame": 4027,
      "start": 2007.5,
      "end": 2014.0,
      "duration": 6.5,
      "original_video": "4TYdFNfMo8k",
      "original_segment_number": 22
    },
    {
      "segment_number": 200,
      "start_frame": 4028,
      "end_frame": 4056,
      "start": 2014.0,
      "end": 2028.5,
      "duration": 14.5,
      "original_video": "4TYdFNfMo8k",
      "original_segment_number": 23
    },
    {
      "segment_number": 201,
      "start_frame": 4057,
      "end_frame": 4078,
      "start": 2028.5,
      "end": 2039.5,
      "duration": 11.0,
      "original_video": "4TYdFNfMo8k",
      "original_segment_number": 24
    },
    {
      "segment_number": 202,
      "start_frame": 4079,
      "end_frame": 4104,
      "start": 2039.5,
      "end": 2052.5,
      "duration": 13.0,
      "original_video": "4TYdFNfMo8k",
      "original_segment_number": 25
    },
    {
      "segment_number": 203,
      "start_frame": 4105,
      "end_frame": 4116,
      "start": 2052.5,
      "end": 2058.5,
      "duration": 6.0,
      "original_video": "4TYdFNfMo8k",
      "original_segment_number": 26
    },
    {
      "segment_number": 204,
      "start_frame": 4117,
      "end_frame": 4143,
      "start": 2058.5,
      "end": 2072.0,
      "duration": 13.5,
      "original_video": "4TYdFNfMo8k",
      "original_segment_number": 27
    },
    {
      "segment_number": 205,
      "start_frame": 4144,
      "end_frame": 4152,
      "start": 2072.0,
      "end": 2076.5,
      "duration": 4.5,
      "original_video": "4TYdFNfMo8k",
      "original_segment_number": 28
    },
    {
      "segment_number": 206,
      "start_frame": 4153,
      "end_frame": 4160,
      "start": 2076.5,
      "end": 2080.5,
      "duration": 4.0,
      "original_video": "4TYdFNfMo8k",
      "original_segment_number": 29
    },
    {
      "segment_number": 207,
      "start_frame": 4161,
      "end_frame": 4177,
      "start": 2080.5,
      "end": 2089.0,
      "duration": 8.5,
      "original_video": "4TYdFNfMo8k",
      "original_segment_number": 30
    },
    {
      "segment_number": 208,
      "start_frame": 4178,
      "end_frame": 4192,
      "start": 2089.0,
      "end": 2096.5,
      "duration": 7.5,
      "original_video": "4TYdFNfMo8k",
      "original_segment_number": 31
    },
    {
      "segment_number": 209,
      "start_frame": 4193,
      "end_frame": 4200,
      "start": 2096.5,
      "end": 2100.5,
      "duration": 4.0,
      "original_video": "4TYdFNfMo8k",
      "original_segment_number": 32
    },
    {
      "segment_number": 210,
      "start_frame": 4201,
      "end_frame": 4213,
      "start": 2100.5,
      "end": 2107.0,
      "duration": 6.5,
      "original_video": "4TYdFNfMo8k",
      "original_segment_number": 33
    },
    {
      "segment_number": 211,
      "start_frame": 4214,
      "end_frame": 4260,
      "start": 2107.0,
      "end": 2130.5,
      "duration": 23.5,
      "original_video": "4TYdFNfMo8k",
      "original_segment_number": 34
    },
    {
      "segment_number": 212,
      "start_frame": 4261,
      "end_frame": 4272,
      "start": 2130.5,
      "end": 2136.5,
      "duration": 6.0,
      "original_video": "4TYdFNfMo8k",
      "original_segment_number": 35
    },
    {
      "segment_number": 213,
      "start_frame": 4273,
      "end_frame": 4277,
      "start": 2136.5,
      "end": 2139.0,
      "duration": 2.5,
      "original_video": "4TYdFNfMo8k",
      "original_segment_number": 36
    },
    {
      "segment_number": 214,
      "start_frame": 4278,
      "end_frame": 4289,
      "start": 2139.0,
      "end": 2145.0,
      "duration": 6.0,
      "original_video": "4TYdFNfMo8k",
      "original_segment_number": 37
    },
    {
      "segment_number": 215,
      "start_frame": 4290,
      "end_frame": 4303,
      "start": 2145.0,
      "end": 2152.0,
      "duration": 7.0,
      "original_video": "4TYdFNfMo8k",
      "original_segment_number": 38
    },
    {
      "segment_number": 216,
      "start_frame": 4304,
      "end_frame": 4319,
      "start": 2152.0,
      "end": 2160.0,
      "duration": 8.0,
      "original_video": "4TYdFNfMo8k",
      "original_segment_number": 39
    },
    {
      "segment_number": 217,
      "start_frame": 4320,
      "end_frame": 4335,
      "start": 2160.0,
      "end": 2168.0,
      "duration": 8.0,
      "original_video": "4TYdFNfMo8k",
      "original_segment_number": 40
    },
    {
      "segment_number": 218,
      "start_frame": 4336,
      "end_frame": 4365,
      "start": 2168.0,
      "end": 2183.0,
      "duration": 15.0,
      "original_video": "4TYdFNfMo8k",
      "original_segment_number": 41
    },
    {
      "segment_number": 219,
      "start_frame": 4366,
      "end_frame": 4371,
      "start": 2183.0,
      "end": 2186.0,
      "duration": 3.0,
      "original_video": "4TYdFNfMo8k",
      "original_segment_number": 42
    },
    {
      "segment_number": 220,
      "start_frame": 4372,
      "end_frame": 4384,
      "start": 2186.0,
      "end": 2192.5,
      "duration": 6.5,
      "original_video": "4TYdFNfMo8k",
      "original_segment_number": 43
    },
    {
      "segment_number": 221,
      "start_frame": 4385,
      "end_frame": 4403,
      "start": 2192.5,
      "end": 2202.0,
      "duration": 9.5,
      "original_video": "4TYdFNfMo8k",
      "original_segment_number": 44
    },
    {
      "segment_number": 222,
      "start_frame": 4404,
      "end_frame": 4425,
      "start": 2202.0,
      "end": 2213.0,
      "duration": 11.0,
      "original_video": "4TYdFNfMo8k",
      "original_segment_number": 45
    },
    {
      "segment_number": 223,
      "start_frame": 4426,
      "end_frame": 4436,
      "start": 2213.0,
      "end": 2218.5,
      "duration": 5.5,
      "original_video": "4TYdFNfMo8k",
      "original_segment_number": 46
    },
    {
      "segment_number": 224,
      "start_frame": 4437,
      "end_frame": 4446,
      "start": 2218.5,
      "end": 2223.5,
      "duration": 5.0,
      "original_video": "4TYdFNfMo8k",
      "original_segment_number": 47
    },
    {
      "segment_number": 225,
      "start_frame": 4447,
      "end_frame": 4464,
      "start": 2223.5,
      "end": 2232.5,
      "duration": 9.0,
      "original_video": "4TYdFNfMo8k",
      "original_segment_number": 48
    },
    {
      "segment_number": 226,
      "start_frame": 4465,
      "end_frame": 4473,
      "start": 2232.5,
      "end": 2237.0,
      "duration": 4.5,
      "original_video": "4TYdFNfMo8k",
      "original_segment_number": 49
    },
    {
      "segment_number": 227,
      "start_frame": 4474,
      "end_frame": 4511,
      "start": 2237.0,
      "end": 2256.0,
      "duration": 19.0,
      "original_video": "4TYdFNfMo8k",
      "original_segment_number": 50
    },
    {
      "segment_number": 228,
      "start_frame": 4512,
      "end_frame": 4521,
      "start": 2256.0,
      "end": 2261.0,
      "duration": 5.0,
      "original_video": "4TYdFNfMo8k",
      "original_segment_number": 51
    },
    {
      "segment_number": 229,
      "start_frame": 4522,
      "end_frame": 4544,
      "start": 2261.0,
      "end": 2272.5,
      "duration": 11.5,
      "original_video": "4TYdFNfMo8k",
      "original_segment_number": 52
    },
    {
      "segment_number": 230,
      "start_frame": 4545,
      "end_frame": 4558,
      "start": 2272.5,
      "end": 2279.5,
      "duration": 7.0,
      "original_video": "4TYdFNfMo8k",
      "original_segment_number": 53
    },
    {
      "segment_number": 231,
      "start_frame": 4559,
      "end_frame": 4573,
      "start": 2279.5,
      "end": 2287.0,
      "duration": 7.5,
      "original_video": "4TYdFNfMo8k",
      "original_segment_number": 54
    },
    {
      "segment_number": 232,
      "start_frame": 4574,
      "end_frame": 4604,
      "start": 2287.0,
      "end": 2302.5,
      "duration": 15.5,
      "original_video": "4TYdFNfMo8k",
      "original_segment_number": 55
    },
    {
      "segment_number": 233,
      "start_frame": 4605,
      "end_frame": 4687,
      "start": 2302.5,
      "end": 2344.0,
      "duration": 41.5,
      "original_video": "4TYdFNfMo8k",
      "original_segment_number": 56
    },
    {
      "segment_number": 234,
      "start_frame": 4688,
      "end_frame": 4708,
      "start": 2344.0,
      "end": 2354.5,
      "duration": 10.5,
      "original_video": "4TYdFNfMo8k",
      "original_segment_number": 57
    },
    {
      "segment_number": 235,
      "start_frame": 4709,
      "end_frame": 4738,
      "start": 2354.5,
      "end": 2369.5,
      "duration": 15.0,
      "original_video": "4TYdFNfMo8k",
      "original_segment_number": 58
    },
    {
      "segment_number": 236,
      "start_frame": 4739,
      "end_frame": 4744,
      "start": 2369.5,
      "end": 2372.5,
      "duration": 3.0,
      "original_video": "4TYdFNfMo8k",
      "original_segment_number": 59
    },
    {
      "segment_number": 237,
      "start_frame": 4745,
      "end_frame": 4842,
      "start": 2372.5,
      "end": 2421.5,
      "duration": 49.0,
      "original_video": "4TYdFNfMo8k",
      "original_segment_number": 60
    },
    {
      "segment_number": 238,
      "start_frame": 4843,
      "end_frame": 4884,
      "start": 2421.5,
      "end": 2442.5,
      "duration": 21.0,
      "original_video": "4TYdFNfMo8k",
      "original_segment_number": 61
    },
    {
      "segment_number": 239,
      "start_frame": 4885,
      "end_frame": 4909,
      "start": 2442.5,
      "end": 2455.0,
      "duration": 12.5,
      "original_video": "4TYdFNfMo8k",
      "original_segment_number": 62
    },
    {
      "segment_number": 240,
      "start_frame": 4910,
      "end_frame": 4915,
      "start": 2455.0,
      "end": 2458.0,
      "duration": 3.0,
      "original_video": "4TYdFNfMo8k",
      "original_segment_number": 63
    },
    {
      "segment_number": 241,
      "start_frame": 4916,
      "end_frame": 4922,
      "start": 2458.0,
      "end": 2461.5,
      "duration": 3.5,
      "original_video": "4TYdFNfMo8k",
      "original_segment_number": 64
    },
    {
      "segment_number": 242,
      "start_frame": 4923,
      "end_frame": 4943,
      "start": 2461.5,
      "end": 2472.0,
      "duration": 10.5,
      "original_video": "4TYdFNfMo8k",
      "original_segment_number": 65
    },
    {
      "segment_number": 243,
      "start_frame": 4944,
      "end_frame": 4955,
      "start": 2472.0,
      "end": 2478.0,
      "duration": 6.0,
      "original_video": "4TYdFNfMo8k",
      "original_segment_number": 66
    },
    {
      "segment_number": 244,
      "start_frame": 4956,
      "end_frame": 4984,
      "start": 2478.0,
      "end": 2492.5,
      "duration": 14.5,
      "original_video": "4TYdFNfMo8k",
      "original_segment_number": 67
    },
    {
      "segment_number": 245,
      "start_frame": 4985,
      "end_frame": 4993,
      "start": 2492.5,
      "end": 2497.0,
      "duration": 4.5,
      "original_video": "4TYdFNfMo8k",
      "original_segment_number": 68
    },
    {
      "segment_number": 246,
      "start_frame": 4994,
      "end_frame": 5023,
      "start": 2497.0,
      "end": 2512.0,
      "duration": 15.0,
      "original_video": "4TYdFNfMo8k",
      "original_segment_number": 69
    },
    {
      "segment_number": 247,
      "start_frame": 5024,
      "end_frame": 5051,
      "start": 2512.0,
      "end": 2526.0,
      "duration": 14.0,
      "original_video": "4TYdFNfMo8k",
      "original_segment_number": 70
    },
    {
      "segment_number": 248,
      "start_frame": 5052,
      "end_frame": 5071,
      "start": 2526.0,
      "end": 2536.0,
      "duration": 10.0,
      "original_video": "4TYdFNfMo8k",
      "original_segment_number": 71
    },
    {
      "segment_number": 249,
      "start_frame": 5072,
      "end_frame": 5116,
      "start": 2536.0,
      "end": 2558.5,
      "duration": 22.5,
      "original_video": "4TYdFNfMo8k",
      "original_segment_number": 72
    },
    {
      "segment_number": 250,
      "start_frame": 5117,
      "end_frame": 5120,
      "start": 2558.5,
      "end": 2560.5,
      "duration": 2.0,
      "original_video": "4TYdFNfMo8k",
      "original_segment_number": 73
    },
    {
      "segment_number": 251,
      "start_frame": 5121,
      "end_frame": 5133,
      "start": 2560.5,
      "end": 2567.0,
      "duration": 6.5,
      "original_video": "4TYdFNfMo8k",
      "original_segment_number": 74
    },
    {
      "segment_number": 252,
      "start_frame": 5134,
      "end_frame": 5175,
      "start": 2567.0,
      "end": 2588.0,
      "duration": 21.0,
      "original_video": "4TYdFNfMo8k",
      "original_segment_number": 75
    },
    {
      "segment_number": 253,
      "start_frame": 5176,
      "end_frame": 5192,
      "start": 2588.0,
      "end": 2596.5,
      "duration": 8.5,
      "original_video": "4TYdFNfMo8k",
      "original_segment_number": 76
    },
    {
      "segment_number": 254,
      "start_frame": 5193,
      "end_frame": 5199,
      "start": 2596.5,
      "end": 2600.0,
      "duration": 3.5,
      "original_video": "4TYdFNfMo8k",
      "original_segment_number": 77
    },
    {
      "segment_number": 255,
      "start_frame": 5200,
      "end_frame": 5208,
      "start": 2600.0,
      "end": 2604.5,
      "duration": 4.5,
      "original_video": "4TYdFNfMo8k",
      "original_segment_number": 78
    },
    {
      "segment_number": 256,
      "start_frame": 5209,
      "end_frame": 5215,
      "start": 2604.5,
      "end": 2608.0,
      "duration": 3.5,
      "original_video": "4TYdFNfMo8k",
      "original_segment_number": 79
    },
    {
      "segment_number": 257,
      "start_frame": 5216,
      "end_frame": 5221,
      "start": 2608.0,
      "end": 2611.0,
      "duration": 3.0,
      "original_video": "4TYdFNfMo8k",
      "original_segment_number": 80
    },
    {
      "segment_number": 258,
      "start_frame": 5222,
      "end_frame": 5248,
      "start": 2611.0,
      "end": 2624.5,
      "duration": 13.5,
      "original_video": "4TYdFNfMo8k",
      "original_segment_number": 81
    },
    {
      "segment_number": 259,
      "start_frame": 5249,
      "end_frame": 5257,
      "start": 2624.5,
      "end": 2629.0,
      "duration": 4.5,
      "original_video": "4TYdFNfMo8k",
      "original_segment_number": 82
    },
    {
      "segment_number": 260,
      "start_frame": 5258,
      "end_frame": 5274,
      "start": 2629.0,
      "end": 2637.5,
      "duration": 8.5,
      "original_video": "4TYdFNfMo8k",
      "original_segment_number": 83
    },
    {
      "segment_number": 261,
      "start_frame": 5275,
      "end_frame": 5281,
      "start": 2637.5,
      "end": 2641.0,
      "duration": 3.5,
      "original_video": "4TYdFNfMo8k",
      "original_segment_number": 84
    },
    {
      "segment_number": 262,
      "start_frame": 5282,
      "end_frame": 5305,
      "start": 2641.0,
      "end": 2653.0,
      "duration": 12.0,
      "original_video": "4TYdFNfMo8k",
      "original_segment_number": 85
    },
    {
      "segment_number": 263,
      "start_frame": 5306,
      "end_frame": 5314,
      "start": 2653.0,
      "end": 2657.5,
      "duration": 4.5,
      "original_video": "4TYdFNfMo8k",
      "original_segment_number": 86
    },
    {
      "segment_number": 264,
      "start_frame": 5315,
      "end_frame": 5341,
      "start": 2657.5,
      "end": 2671.0,
      "duration": 13.5,
      "original_video": "4TYdFNfMo8k",
      "original_segment_number": 87
    },
    {
      "segment_number": 265,
      "start_frame": 5342,
      "end_frame": 5362,
      "start": 2671.0,
      "end": 2681.5,
      "duration": 10.5,
      "original_video": "4TYdFNfMo8k",
      "original_segment_number": 88
    },
    {
      "segment_number": 266,
      "start_frame": 5363,
      "end_frame": 5383,
      "start": 2681.5,
      "end": 2692.0,
      "duration": 10.5,
      "original_video": "4TYdFNfMo8k",
      "original_segment_number": 89
    },
    {
      "segment_number": 267,
      "start_frame": 5384,
      "end_frame": 5396,
      "start": 2692.0,
      "end": 2698.5,
      "duration": 6.5,
      "original_video": "4TYdFNfMo8k",
      "original_segment_number": 90
    },
    {
      "segment_number": 268,
      "start_frame": 5397,
      "end_frame": 5402,
      "start": 2698.5,
      "end": 2701.5,
      "duration": 3.0,
      "original_video": "4TYdFNfMo8k",
      "original_segment_number": 91
    },
    {
      "segment_number": 269,
      "start_frame": 5403,
      "end_frame": 5415,
      "start": 2701.5,
      "end": 2708.0,
      "duration": 6.5,
      "original_video": "4TYdFNfMo8k",
      "original_segment_number": 92
    },
    {
      "segment_number": 270,
      "start_frame": 5416,
      "end_frame": 5443,
      "start": 2708.0,
      "end": 2722.0,
      "duration": 14.0,
      "original_video": "4TYdFNfMo8k",
      "original_segment_number": 93
    },
    {
      "segment_number": 271,
      "start_frame": 5444,
      "end_frame": 5451,
      "start": 2722.0,
      "end": 2726.0,
      "duration": 4.0,
      "original_video": "4TYdFNfMo8k",
      "original_segment_number": 94
    },
    {
      "segment_number": 272,
      "start_frame": 5452,
      "end_frame": 5462,
      "start": 2726.0,
      "end": 2731.5,
      "duration": 5.5,
      "original_video": "4TYdFNfMo8k",
      "original_segment_number": 95
    },
    {
      "segment_number": 273,
      "start_frame": 5463,
      "end_frame": 5482,
      "start": 2731.5,
      "end": 2741.5,
      "duration": 10.0,
      "original_video": "4TYdFNfMo8k",
      "original_segment_number": 96
    },
    {
      "segment_number": 274,
      "start_frame": 5483,
      "end_frame": 5495,
      "start": 2741.5,
      "end": 2748.0,
      "duration": 6.5,
      "original_video": "4TYdFNfMo8k",
      "original_segment_number": 97
    },
    {
      "segment_number": 275,
      "start_frame": 5496,
      "end_frame": 5508,
      "start": 2748.0,
      "end": 2754.5,
      "duration": 6.5,
      "original_video": "4TYdFNfMo8k",
      "original_segment_number": 98
    },
    {
      "segment_number": 276,
      "start_frame": 5509,
      "end_frame": 5530,
      "start": 2754.5,
      "end": 2765.5,
      "duration": 11.0,
      "original_video": "4TYdFNfMo8k",
      "original_segment_number": 99
    },
    {
      "segment_number": 277,
      "start_frame": 5531,
      "end_frame": 5549,
      "start": 2765.5,
      "end": 2775.0,
      "duration": 9.5,
      "original_video": "4TYdFNfMo8k",
      "original_segment_number": 100
    },
    {
      "segment_number": 278,
      "start_frame": 5550,
      "end_frame": 5590,
      "start": 2775.0,
      "end": 2795.5,
      "duration": 20.5,
      "original_video": "4TYdFNfMo8k",
      "original_segment_number": 101
    },
    {
      "segment_number": 279,
      "start_frame": 5591,
      "end_frame": 5597,
      "start": 2795.5,
      "end": 2799.0,
      "duration": 3.5,
      "original_video": "4TYdFNfMo8k",
      "original_segment_number": 102
    },
    {
      "segment_number": 280,
      "start_frame": 5598,
      "end_frame": 5632,
      "start": 2799.0,
      "end": 2816.5,
      "duration": 17.5,
      "original_video": "4TYdFNfMo8k",
      "original_segment_number": 103
    },
    {
      "segment_number": 281,
      "start_frame": 5633,
      "end_frame": 5654,
      "start": 2816.5,
      "end": 2827.5,
      "duration": 11.0,
      "original_video": "4TYdFNfMo8k",
      "original_segment_number": 104
    },
    {
      "segment_number": 282,
      "start_frame": 5655,
      "end_frame": 5665,
      "start": 2827.5,
      "end": 2833.0,
      "duration": 5.5,
      "original_video": "4TYdFNfMo8k",
      "original_segment_number": 105
    },
    {
      "segment_number": 283,
      "start_frame": 5666,
      "end_frame": 5671,
      "start": 2833.0,
      "end": 2836.0,
      "duration": 3.0,
      "original_video": "4TYdFNfMo8k",
      "original_segment_number": 106
    },
    {
      "segment_number": 284,
      "start_frame": 5672,
      "end_frame": 5679,
      "start": 2836.0,
      "end": 2840.0,
      "duration": 4.0,
      "original_video": "4TYdFNfMo8k",
      "original_segment_number": 107
    },
    {
      "segment_number": 285,
      "start_frame": 5680,
      "end_frame": 5705,
      "start": 2840.0,
      "end": 2853.0,
      "duration": 13.0,
      "original_video": "4TYdFNfMo8k",
      "original_segment_number": 108
    },
    {
      "segment_number": 286,
      "start_frame": 5706,
      "end_frame": 5740,
      "start": 2853.0,
      "end": 2870.5,
      "duration": 17.5,
      "original_video": "4TYdFNfMo8k",
      "original_segment_number": 109
    },
    {
      "segment_number": 287,
      "start_frame": 5741,
      "end_frame": 5765,
      "start": 2870.5,
      "end": 2883.0,
      "duration": 12.5,
      "original_video": "4TYdFNfMo8k",
      "original_segment_number": 110
    },
    {
      "segment_number": 288,
      "start_frame": 5766,
      "end_frame": 5806,
      "start": 2883.0,
      "end": 2903.5,
      "duration": 20.5,
      "original_video": "4TYdFNfMo8k",
      "original_segment_number": 111
    },
    {
      "segment_number": 289,
      "start_frame": 5807,
      "end_frame": 5826,
      "start": 2903.5,
      "end": 2913.5,
      "duration": 10.0,
      "original_video": "HCOGXLr1ztA",
      "original_segment_number": 0
    },
    {
      "segment_number": 290,
      "start_frame": 5827,
      "end_frame": 5833,
      "start": 2913.5,
      "end": 2917.0,
      "duration": 3.5,
      "original_video": "HCOGXLr1ztA",
      "original_segment_number": 1
    },
    {
      "segment_number": 291,
      "start_frame": 5834,
      "end_frame": 5852,
      "start": 2917.0,
      "end": 2926.5,
      "duration": 9.5,
      "original_video": "HCOGXLr1ztA",
      "original_segment_number": 2
    },
    {
      "segment_number": 292,
      "start_frame": 5853,
      "end_frame": 5895,
      "start": 2926.5,
      "end": 2948.0,
      "duration": 21.5,
      "original_video": "HCOGXLr1ztA",
      "original_segment_number": 3
    },
    {
      "segment_number": 293,
      "start_frame": 5896,
      "end_frame": 5900,
      "start": 2948.0,
      "end": 2950.5,
      "duration": 2.5,
      "original_video": "HCOGXLr1ztA",
      "original_segment_number": 4
    },
    {
      "segment_number": 294,
      "start_frame": 5901,
      "end_frame": 5908,
      "start": 2950.5,
      "end": 2954.5,
      "duration": 4.0,
      "original_video": "HCOGXLr1ztA",
      "original_segment_number": 5
    },
    {
      "segment_number": 295,
      "start_frame": 5909,
      "end_frame": 5922,
      "start": 2954.5,
      "end": 2961.5,
      "duration": 7.0,
      "original_video": "HCOGXLr1ztA",
      "original_segment_number": 6
    },
    {
      "segment_number": 296,
      "start_frame": 5923,
      "end_frame": 5930,
      "start": 2961.5,
      "end": 2965.5,
      "duration": 4.0,
      "original_video": "HCOGXLr1ztA",
      "original_segment_number": 7
    },
    {
      "segment_number": 297,
      "start_frame": 5931,
      "end_frame": 5950,
      "start": 2965.5,
      "end": 2975.5,
      "duration": 10.0,
      "original_video": "HCOGXLr1ztA",
      "original_segment_number": 8
    },
    {
      "segment_number": 298,
      "start_frame": 5951,
      "end_frame": 5957,
      "start": 2975.5,
      "end": 2979.0,
      "duration": 3.5,
      "original_video": "HCOGXLr1ztA",
      "original_segment_number": 9
    },
    {
      "segment_number": 299,
      "start_frame": 5958,
      "end_frame": 5977,
      "start": 2979.0,
      "end": 2989.0,
      "duration": 10.0,
      "original_video": "HCOGXLr1ztA",
      "original_segment_number": 10
    },
    {
      "segment_number": 300,
      "start_frame": 5978,
      "end_frame": 6011,
      "start": 2989.0,
      "end": 3006.0,
      "duration": 17.0,
      "original_video": "HCOGXLr1ztA",
      "original_segment_number": 11
    },
    {
      "segment_number": 301,
      "start_frame": 6012,
      "end_frame": 6017,
      "start": 3006.0,
      "end": 3009.0,
      "duration": 3.0,
      "original_video": "HCOGXLr1ztA",
      "original_segment_number": 12
    },
    {
      "segment_number": 302,
      "start_frame": 6018,
      "end_frame": 6034,
      "start": 3009.0,
      "end": 3017.5,
      "duration": 8.5,
      "original_video": "HCOGXLr1ztA",
      "original_segment_number": 13
    },
    {
      "segment_number": 303,
      "start_frame": 6035,
      "end_frame": 6040,
      "start": 3017.5,
      "end": 3020.5,
      "duration": 3.0,
      "original_video": "HCOGXLr1ztA",
      "original_segment_number": 14
    },
    {
      "segment_number": 304,
      "start_frame": 6041,
      "end_frame": 6067,
      "start": 3020.5,
      "end": 3034.0,
      "duration": 13.5,
      "original_video": "HCOGXLr1ztA",
      "original_segment_number": 15
    },
    {
      "segment_number": 305,
      "start_frame": 6068,
      "end_frame": 6141,
      "start": 3034.0,
      "end": 3071.0,
      "duration": 37.0,
      "original_video": "HCOGXLr1ztA",
      "original_segment_number": 16
    },
    {
      "segment_number": 306,
      "start_frame": 6142,
      "end_frame": 6161,
      "start": 3071.0,
      "end": 3081.0,
      "duration": 10.0,
      "original_video": "HCOGXLr1ztA",
      "original_segment_number": 17
    },
    {
      "segment_number": 307,
      "start_frame": 6162,
      "end_frame": 6186,
      "start": 3081.0,
      "end": 3093.5,
      "duration": 12.5,
      "original_video": "HCOGXLr1ztA",
      "original_segment_number": 18
    },
    {
      "segment_number": 308,
      "start_frame": 6187,
      "end_frame": 6237,
      "start": 3093.5,
      "end": 3119.0,
      "duration": 25.5,
      "original_video": "HCOGXLr1ztA",
      "original_segment_number": 19
    },
    {
      "segment_number": 309,
      "start_frame": 6238,
      "end_frame": 6246,
      "start": 3119.0,
      "end": 3123.5,
      "duration": 4.5,
      "original_video": "HCOGXLr1ztA",
      "original_segment_number": 20
    },
    {
      "segment_number": 310,
      "start_frame": 6247,
      "end_frame": 6267,
      "start": 3123.5,
      "end": 3134.0,
      "duration": 10.5,
      "original_video": "HCOGXLr1ztA",
      "original_segment_number": 21
    },
    {
      "segment_number": 311,
      "start_frame": 6268,
      "end_frame": 6280,
      "start": 3134.0,
      "end": 3140.5,
      "duration": 6.5,
      "original_video": "HCOGXLr1ztA",
      "original_segment_number": 22
    },
    {
      "segment_number": 312,
      "start_frame": 6281,
      "end_frame": 6322,
      "start": 3140.5,
      "end": 3161.5,
      "duration": 21.0,
      "original_video": "HCOGXLr1ztA",
      "original_segment_number": 23
    },
    {
      "segment_number": 313,
      "start_frame": 6323,
      "end_frame": 6349,
      "start": 3161.5,
      "end": 3175.0,
      "duration": 13.5,
      "original_video": "HCOGXLr1ztA",
      "original_segment_number": 24
    },
    {
      "segment_number": 314,
      "start_frame": 6350,
      "end_frame": 6385,
      "start": 3175.0,
      "end": 3193.0,
      "duration": 18.0,
      "original_video": "HCOGXLr1ztA",
      "original_segment_number": 25
    },
    {
      "segment_number": 315,
      "start_frame": 6386,
      "end_frame": 6392,
      "start": 3193.0,
      "end": 3196.5,
      "duration": 3.5,
      "original_video": "HCOGXLr1ztA",
      "original_segment_number": 26
    },
    {
      "segment_number": 316,
      "start_frame": 6393,
      "end_frame": 6403,
      "start": 3196.5,
      "end": 3202.0,
      "duration": 5.5,
      "original_video": "HCOGXLr1ztA",
      "original_segment_number": 27
    },
    {
      "segment_number": 317,
      "start_frame": 6404,
      "end_frame": 6452,
      "start": 3202.0,
      "end": 3226.5,
      "duration": 24.5,
      "original_video": "HCOGXLr1ztA",
      "original_segment_number": 28
    },
    {
      "segment_number": 318,
      "start_frame": 6453,
      "end_frame": 6465,
      "start": 3226.5,
      "end": 3233.0,
      "duration": 6.5,
      "original_video": "HCOGXLr1ztA",
      "original_segment_number": 29
    },
    {
      "segment_number": 319,
      "start_frame": 6466,
      "end_frame": 6484,
      "start": 3233.0,
      "end": 3242.5,
      "duration": 9.5,
      "original_video": "HCOGXLr1ztA",
      "original_segment_number": 30
    },
    {
      "segment_number": 320,
      "start_frame": 6485,
      "end_frame": 6562,
      "start": 3242.5,
      "end": 3281.5,
      "duration": 39.0,
      "original_video": "HCOGXLr1ztA",
      "original_segment_number": 31
    },
    {
      "segment_number": 321,
      "start_frame": 6563,
      "end_frame": 6585,
      "start": 3281.5,
      "end": 3293.0,
      "duration": 11.5,
      "original_video": "HCOGXLr1ztA",
      "original_segment_number": 32
    },
    {
      "segment_number": 322,
      "start_frame": 6586,
      "end_frame": 6596,
      "start": 3293.0,
      "end": 3298.5,
      "duration": 5.5,
      "original_video": "HCOGXLr1ztA",
      "original_segment_number": 33
    },
    {
      "segment_number": 323,
      "start_frame": 6597,
      "end_frame": 6603,
      "start": 3298.5,
      "end": 3302.0,
      "duration": 3.5,
      "original_video": "HCOGXLr1ztA",
      "original_segment_number": 34
    },
    {
      "segment_number": 324,
      "start_frame": 6604,
      "end_frame": 6618,
      "start": 3302.0,
      "end": 3309.5,
      "duration": 7.5,
      "original_video": "HCOGXLr1ztA",
      "original_segment_number": 35
    },
    {
      "segment_number": 325,
      "start_frame": 6619,
      "end_frame": 6650,
      "start": 3309.5,
      "end": 3325.5,
      "duration": 16.0,
      "original_video": "HCOGXLr1ztA",
      "original_segment_number": 36
    },
    {
      "segment_number": 326,
      "start_frame": 6651,
      "end_frame": 6671,
      "start": 3325.5,
      "end": 3336.0,
      "duration": 10.5,
      "original_video": "HCOGXLr1ztA",
      "original_segment_number": 37
    },
    {
      "segment_number": 327,
      "start_frame": 6672,
      "end_frame": 6675,
      "start": 3336.0,
      "end": 3338.0,
      "duration": 2.0,
      "original_video": "HCOGXLr1ztA",
      "original_segment_number": 38
    },
    {
      "segment_number": 328,
      "start_frame": 6676,
      "end_frame": 6687,
      "start": 3338.0,
      "end": 3344.0,
      "duration": 6.0,
      "original_video": "HCOGXLr1ztA",
      "original_segment_number": 39
    },
    {
      "segment_number": 329,
      "start_frame": 6688,
      "end_frame": 6724,
      "start": 3344.0,
      "end": 3362.5,
      "duration": 18.5,
      "original_video": "HCOGXLr1ztA",
      "original_segment_number": 40
    },
    {
      "segment_number": 330,
      "start_frame": 6725,
      "end_frame": 6762,
      "start": 3362.5,
      "end": 3381.5,
      "duration": 19.0,
      "original_video": "HCOGXLr1ztA",
      "original_segment_number": 41
    },
    {
      "segment_number": 331,
      "start_frame": 6763,
      "end_frame": 6774,
      "start": 3381.5,
      "end": 3387.5,
      "duration": 6.0,
      "original_video": "HCOGXLr1ztA",
      "original_segment_number": 42
    },
    {
      "segment_number": 332,
      "start_frame": 6775,
      "end_frame": 6802,
      "start": 3387.5,
      "end": 3401.5,
      "duration": 14.0,
      "original_video": "HCOGXLr1ztA",
      "original_segment_number": 43
    },
    {
      "segment_number": 333,
      "start_frame": 6803,
      "end_frame": 6816,
      "start": 3401.5,
      "end": 3408.5,
      "duration": 7.0,
      "original_video": "HCOGXLr1ztA",
      "original_segment_number": 44
    },
    {
      "segment_number": 334,
      "start_frame": 6817,
      "end_frame": 6823,
      "start": 3408.5,
      "end": 3412.0,
      "duration": 3.5,
      "original_video": "HCOGXLr1ztA",
      "original_segment_number": 45
    },
    {
      "segment_number": 335,
      "start_frame": 6824,
      "end_frame": 6830,
      "start": 3412.0,
      "end": 3415.5,
      "duration": 3.5,
      "original_video": "HCOGXLr1ztA",
      "original_segment_number": 46
    },
    {
      "segment_number": 336,
      "start_frame": 6831,
      "end_frame": 6841,
      "start": 3415.5,
      "end": 3421.0,
      "duration": 5.5,
      "original_video": "HCOGXLr1ztA",
      "original_segment_number": 47
    },
    {
      "segment_number": 337,
      "start_frame": 6842,
      "end_frame": 6856,
      "start": 3421.0,
      "end": 3428.5,
      "duration": 7.5,
      "original_video": "HCOGXLr1ztA",
      "original_segment_number": 48
    },
    {
      "segment_number": 338,
      "start_frame": 6857,
      "end_frame": 6894,
      "start": 3428.5,
      "end": 3447.5,
      "duration": 19.0,
      "original_video": "HCOGXLr1ztA",
      "original_segment_number": 49
    },
    {
      "segment_number": 339,
      "start_frame": 6895,
      "end_frame": 6908,
      "start": 3447.5,
      "end": 3454.5,
      "duration": 7.0,
      "original_video": "HCOGXLr1ztA",
      "original_segment_number": 50
    },
    {
      "segment_number": 340,
      "start_frame": 6909,
      "end_frame": 6932,
      "start": 3454.5,
      "end": 3466.5,
      "duration": 12.0,
      "original_video": "HCOGXLr1ztA",
      "original_segment_number": 51
    },
    {
      "segment_number": 341,
      "start_frame": 6933,
      "end_frame": 6938,
      "start": 3466.5,
      "end": 3469.5,
      "duration": 3.0,
      "original_video": "HCOGXLr1ztA",
      "original_segment_number": 52
    },
    {
      "segment_number": 342,
      "start_frame": 6939,
      "end_frame": 6943,
      "start": 3469.5,
      "end": 3472.0,
      "duration": 2.5,
      "original_video": "HCOGXLr1ztA",
      "original_segment_number": 53
    },
    {
      "segment_number": 343,
      "start_frame": 6944,
      "end_frame": 6959,
      "start": 3472.0,
      "end": 3480.0,
      "duration": 8.0,
      "original_video": "HCOGXLr1ztA",
      "original_segment_number": 54
    },
    {
      "segment_number": 344,
      "start_frame": 6960,
      "end_frame": 6968,
      "start": 3480.0,
      "end": 3484.5,
      "duration": 4.5,
      "original_video": "HCOGXLr1ztA",
      "original_segment_number": 55
    },
    {
      "segment_number": 345,
      "start_frame": 6969,
      "end_frame": 6990,
      "start": 3484.5,
      "end": 3495.5,
      "duration": 11.0,
      "original_video": "HCOGXLr1ztA",
      "original_segment_number": 56
    },
    {
      "segment_number": 346,
      "start_frame": 6991,
      "end_frame": 7005,
      "start": 3495.5,
      "end": 3503.0,
      "duration": 7.5,
      "original_video": "HCOGXLr1ztA",
      "original_segment_number": 57
    },
    {
      "segment_number": 347,
      "start_frame": 7006,
      "end_frame": 7018,
      "start": 3503.0,
      "end": 3509.5,
      "duration": 6.5,
      "original_video": "HCOGXLr1ztA",
      "original_segment_number": 58
    },
    {
      "segment_number": 348,
      "start_frame": 7019,
      "end_frame": 7028,
      "start": 3509.5,
      "end": 3514.5,
      "duration": 5.0,
      "original_video": "HCOGXLr1ztA",
      "original_segment_number": 59
    },
    {
      "segment_number": 349,
      "start_frame": 7029,
      "end_frame": 7053,
      "start": 3514.5,
      "end": 3527.0,
      "duration": 12.5,
      "original_video": "HCOGXLr1ztA",
      "original_segment_number": 60
    },
    {
      "segment_number": 350,
      "start_frame": 7054,
      "end_frame": 7069,
      "start": 3527.0,
      "end": 3535.0,
      "duration": 8.0,
      "original_video": "HCOGXLr1ztA",
      "original_segment_number": 61
    },
    {
      "segment_number": 351,
      "start_frame": 7070,
      "end_frame": 7094,
      "start": 3535.0,
      "end": 3547.5,
      "duration": 12.5,
      "original_video": "HCOGXLr1ztA",
      "original_segment_number": 62
    },
    {
      "segment_number": 352,
      "start_frame": 7095,
      "end_frame": 7107,
      "start": 3547.5,
      "end": 3554.0,
      "duration": 6.5,
      "original_video": "HCOGXLr1ztA",
      "original_segment_number": 63
    },
    {
      "segment_number": 353,
      "start_frame": 7108,
      "end_frame": 7127,
      "start": 3554.0,
      "end": 3564.0,
      "duration": 10.0,
      "original_video": "HCOGXLr1ztA",
      "original_segment_number": 64
    },
    {
      "segment_number": 354,
      "start_frame": 7128,
      "end_frame": 7139,
      "start": 3564.0,
      "end": 3570.0,
      "duration": 6.0,
      "original_video": "HCOGXLr1ztA",
      "original_segment_number": 65
    },
    {
      "segment_number": 355,
      "start_frame": 7140,
      "end_frame": 7152,
      "start": 3570.0,
      "end": 3576.5,
      "duration": 6.5,
      "original_video": "HCOGXLr1ztA",
      "original_segment_number": 66
    },
    {
      "segment_number": 356,
      "start_frame": 7153,
      "end_frame": 7159,
      "start": 3576.5,
      "end": 3580.0,
      "duration": 3.5,
      "original_video": "HCOGXLr1ztA",
      "original_segment_number": 67
    },
    {
      "segment_number": 357,
      "start_frame": 7160,
      "end_frame": 7166,
      "start": 3580.0,
      "end": 3583.5,
      "duration": 3.5,
      "original_video": "HCOGXLr1ztA",
      "original_segment_number": 68
    },
    {
      "segment_number": 358,
      "start_frame": 7167,
      "end_frame": 7179,
      "start": 3583.5,
      "end": 3590.0,
      "duration": 6.5,
      "original_video": "HCOGXLr1ztA",
      "original_segment_number": 69
    },
    {
      "segment_number": 359,
      "start_frame": 7180,
      "end_frame": 7199,
      "start": 3590.0,
      "end": 3600.0,
      "duration": 10.0,
      "original_video": "HCOGXLr1ztA",
      "original_segment_number": 70
    },
    {
      "segment_number": 360,
      "start_frame": 7200,
      "end_frame": 7205,
      "start": 3600.0,
      "end": 3603.0,
      "duration": 3.0,
      "original_video": "HCOGXLr1ztA",
      "original_segment_number": 71
    },
    {
      "segment_number": 361,
      "start_frame": 7206,
      "end_frame": 7277,
      "start": 3603.0,
      "end": 3639.0,
      "duration": 36.0,
      "original_video": "HCOGXLr1ztA",
      "original_segment_number": 72
    },
    {
      "segment_number": 362,
      "start_frame": 7278,
      "end_frame": 7291,
      "start": 3639.0,
      "end": 3646.0,
      "duration": 7.0,
      "original_video": "HCOGXLr1ztA",
      "original_segment_number": 73
    },
    {
      "segment_number": 363,
      "start_frame": 7292,
      "end_frame": 7314,
      "start": 3646.0,
      "end": 3657.5,
      "duration": 11.5,
      "original_video": "HCOGXLr1ztA",
      "original_segment_number": 74
    },
    {
      "segment_number": 364,
      "start_frame": 7315,
      "end_frame": 7344,
      "start": 3657.5,
      "end": 3672.5,
      "duration": 15.0,
      "original_video": "VmVxNRu4uIo",
      "original_segment_number": 0
    },
    {
      "segment_number": 365,
      "start_frame": 7345,
      "end_frame": 7350,
      "start": 3672.5,
      "end": 3675.5,
      "duration": 3.0,
      "original_video": "VmVxNRu4uIo",
      "original_segment_number": 1
    },
    {
      "segment_number": 366,
      "start_frame": 7351,
      "end_frame": 7356,
      "start": 3675.5,
      "end": 3678.5,
      "duration": 3.0,
      "original_video": "VmVxNRu4uIo",
      "original_segment_number": 2
    },
    {
      "segment_number": 367,
      "start_frame": 7357,
      "end_frame": 7363,
      "start": 3678.5,
      "end": 3682.0,
      "duration": 3.5,
      "original_video": "VmVxNRu4uIo",
      "original_segment_number": 3
    },
    {
      "segment_number": 368,
      "start_frame": 7364,
      "end_frame": 7371,
      "start": 3682.0,
      "end": 3686.0,
      "duration": 4.0,
      "original_video": "VmVxNRu4uIo",
      "original_segment_number": 4
    },
    {
      "segment_number": 369,
      "start_frame": 7372,
      "end_frame": 7396,
      "start": 3686.0,
      "end": 3698.5,
      "duration": 12.5,
      "original_video": "VmVxNRu4uIo",
      "original_segment_number": 5
    },
    {
      "segment_number": 370,
      "start_frame": 7397,
      "end_frame": 7405,
      "start": 3698.5,
      "end": 3703.0,
      "duration": 4.5,
      "original_video": "VmVxNRu4uIo",
      "original_segment_number": 6
    },
    {
      "segment_number": 371,
      "start_frame": 7406,
      "end_frame": 7431,
      "start": 3703.0,
      "end": 3716.0,
      "duration": 13.0,
      "original_video": "VmVxNRu4uIo",
      "original_segment_number": 7
    },
    {
      "segment_number": 372,
      "start_frame": 7432,
      "end_frame": 7447,
      "start": 3716.0,
      "end": 3724.0,
      "duration": 8.0,
      "original_video": "VmVxNRu4uIo",
      "original_segment_number": 8
    },
    {
      "segment_number": 373,
      "start_frame": 7448,
      "end_frame": 7459,
      "start": 3724.0,
      "end": 3730.0,
      "duration": 6.0,
      "original_video": "VmVxNRu4uIo",
      "original_segment_number": 9
    },
    {
      "segment_number": 374,
      "start_frame": 7460,
      "end_frame": 7477,
      "start": 3730.0,
      "end": 3739.0,
      "duration": 9.0,
      "original_video": "VmVxNRu4uIo",
      "original_segment_number": 10
    },
    {
      "segment_number": 375,
      "start_frame": 7478,
      "end_frame": 7492,
      "start": 3739.0,
      "end": 3746.5,
      "duration": 7.5,
      "original_video": "VmVxNRu4uIo",
      "original_segment_number": 11
    },
    {
      "segment_number": 376,
      "start_frame": 7493,
      "end_frame": 7532,
      "start": 3746.5,
      "end": 3766.5,
      "duration": 20.0,
      "original_video": "VmVxNRu4uIo",
      "original_segment_number": 12
    },
    {
      "segment_number": 377,
      "start_frame": 7533,
      "end_frame": 7564,
      "start": 3766.5,
      "end": 3782.5,
      "duration": 16.0,
      "original_video": "VmVxNRu4uIo",
      "original_segment_number": 13
    },
    {
      "segment_number": 378,
      "start_frame": 7565,
      "end_frame": 7618,
      "start": 3782.5,
      "end": 3809.5,
      "duration": 27.0,
      "original_video": "VmVxNRu4uIo",
      "original_segment_number": 14
    },
    {
      "segment_number": 379,
      "start_frame": 7619,
      "end_frame": 7646,
      "start": 3809.5,
      "end": 3823.5,
      "duration": 14.0,
      "original_video": "VmVxNRu4uIo",
      "original_segment_number": 15
    },
    {
      "segment_number": 380,
      "start_frame": 7647,
      "end_frame": 7656,
      "start": 3823.5,
      "end": 3828.5,
      "duration": 5.0,
      "original_video": "VmVxNRu4uIo",
      "original_segment_number": 16
    },
    {
      "segment_number": 381,
      "start_frame": 7657,
      "end_frame": 7663,
      "start": 3828.5,
      "end": 3832.0,
      "duration": 3.5,
      "original_video": "VmVxNRu4uIo",
      "original_segment_number": 17
    },
    {
      "segment_number": 382,
      "start_frame": 7664,
      "end_frame": 7693,
      "start": 3832.0,
      "end": 3847.0,
      "duration": 15.0,
      "original_video": "VmVxNRu4uIo",
      "original_segment_number": 18
    },
    {
      "segment_number": 383,
      "start_frame": 7694,
      "end_frame": 7715,
      "start": 3847.0,
      "end": 3858.0,
      "duration": 11.0,
      "original_video": "VmVxNRu4uIo",
      "original_segment_number": 19
    },
    {
      "segment_number": 384,
      "start_frame": 7716,
      "end_frame": 7724,
      "start": 3858.0,
      "end": 3862.5,
      "duration": 4.5,
      "original_video": "VmVxNRu4uIo",
      "original_segment_number": 20
    },
    {
      "segment_number": 385,
      "start_frame": 7725,
      "end_frame": 7740,
      "start": 3862.5,
      "end": 3870.5,
      "duration": 8.0,
      "original_video": "VmVxNRu4uIo",
      "original_segment_number": 21
    },
    {
      "segment_number": 386,
      "start_frame": 7741,
      "end_frame": 7749,
      "start": 3870.5,
      "end": 3875.0,
      "duration": 4.5,
      "original_video": "VmVxNRu4uIo",
      "original_segment_number": 22
    },
    {
      "segment_number": 387,
      "start_frame": 7750,
      "end_frame": 7761,
      "start": 3875.0,
      "end": 3881.0,
      "duration": 6.0,
      "original_video": "VmVxNRu4uIo",
      "original_segment_number": 23
    },
    {
      "segment_number": 388,
      "start_frame": 7762,
      "end_frame": 7786,
      "start": 3881.0,
      "end": 3893.5,
      "duration": 12.5,
      "original_video": "VmVxNRu4uIo",
      "original_segment_number": 24
    },
    {
      "segment_number": 389,
      "start_frame": 7787,
      "end_frame": 7811,
      "start": 3893.5,
      "end": 3906.0,
      "duration": 12.5,
      "original_video": "VmVxNRu4uIo",
      "original_segment_number": 25
    },
    {
      "segment_number": 390,
      "start_frame": 7812,
      "end_frame": 7830,
      "start": 3906.0,
      "end": 3915.5,
      "duration": 9.5,
      "original_video": "VmVxNRu4uIo",
      "original_segment_number": 26
    },
    {
      "segment_number": 391,
      "start_frame": 7831,
      "end_frame": 7863,
      "start": 3915.5,
      "end": 3932.0,
      "duration": 16.5,
      "original_video": "VmVxNRu4uIo",
      "original_segment_number": 27
    },
    {
      "segment_number": 392,
      "start_frame": 7864,
      "end_frame": 7867,
      "start": 3932.0,
      "end": 3934.0,
      "duration": 2.0,
      "original_video": "VmVxNRu4uIo",
      "original_segment_number": 28
    },
    {
      "segment_number": 393,
      "start_frame": 7868,
      "end_frame": 7881,
      "start": 3934.0,
      "end": 3941.0,
      "duration": 7.0,
      "original_video": "VmVxNRu4uIo",
      "original_segment_number": 29
    },
    {
      "segment_number": 394,
      "start_frame": 7882,
      "end_frame": 7904,
      "start": 3941.0,
      "end": 3952.5,
      "duration": 11.5,
      "original_video": "VmVxNRu4uIo",
      "original_segment_number": 30
    },
    {
      "segment_number": 395,
      "start_frame": 7905,
      "end_frame": 7913,
      "start": 3952.5,
      "end": 3957.0,
      "duration": 4.5,
      "original_video": "VmVxNRu4uIo",
      "original_segment_number": 31
    },
    {
      "segment_number": 396,
      "start_frame": 7914,
      "end_frame": 7927,
      "start": 3957.0,
      "end": 3964.0,
      "duration": 7.0,
      "original_video": "VmVxNRu4uIo",
      "original_segment_number": 32
    },
    {
      "segment_number": 397,
      "start_frame": 7928,
      "end_frame": 7932,
      "start": 3964.0,
      "end": 3966.5,
      "duration": 2.5,
      "original_video": "VmVxNRu4uIo",
      "original_segment_number": 33
    },
    {
      "segment_number": 398,
      "start_frame": 7933,
      "end_frame": 7951,
      "start": 3966.5,
      "end": 3976.0,
      "duration": 9.5,
      "original_video": "VmVxNRu4uIo",
      "original_segment_number": 34
    },
    {
      "segment_number": 399,
      "start_frame": 7952,
      "end_frame": 7988,
      "start": 3976.0,
      "end": 3994.5,
      "duration": 18.5,
      "original_video": "VmVxNRu4uIo",
      "original_segment_number": 35
    },
    {
      "segment_number": 400,
      "start_frame": 7989,
      "end_frame": 7998,
      "start": 3994.5,
      "end": 3999.5,
      "duration": 5.0,
      "original_video": "VmVxNRu4uIo",
      "original_segment_number": 36
    },
    {
      "segment_number": 401,
      "start_frame": 7999,
      "end_frame": 8023,
      "start": 3999.5,
      "end": 4012.0,
      "duration": 12.5,
      "original_video": "VmVxNRu4uIo",
      "original_segment_number": 37
    },
    {
      "segment_number": 402,
      "start_frame": 8024,
      "end_frame": 8030,
      "start": 4012.0,
      "end": 4015.5,
      "duration": 3.5,
      "original_video": "VmVxNRu4uIo",
      "original_segment_number": 38
    },
    {
      "segment_number": 403,
      "start_frame": 8031,
      "end_frame": 8048,
      "start": 4015.5,
      "end": 4024.5,
      "duration": 9.0,
      "original_video": "VmVxNRu4uIo",
      "original_segment_number": 39
    },
    {
      "segment_number": 404,
      "start_frame": 8049,
      "end_frame": 8066,
      "start": 4024.5,
      "end": 4033.5,
      "duration": 9.0,
      "original_video": "VmVxNRu4uIo",
      "original_segment_number": 40
    },
    {
      "segment_number": 405,
      "start_frame": 8067,
      "end_frame": 8102,
      "start": 4033.5,
      "end": 4051.5,
      "duration": 18.0,
      "original_video": "VmVxNRu4uIo",
      "original_segment_number": 41
    },
    {
      "segment_number": 406,
      "start_frame": 8103,
      "end_frame": 8119,
      "start": 4051.5,
      "end": 4060.0,
      "duration": 8.5,
      "original_video": "VmVxNRu4uIo",
      "original_segment_number": 42
    },
    {
      "segment_number": 407,
      "start_frame": 8120,
      "end_frame": 8180,
      "start": 4060.0,
      "end": 4090.5,
      "duration": 30.5,
      "original_video": "VmVxNRu4uIo",
      "original_segment_number": 43
    },
    {
      "segment_number": 408,
      "start_frame": 8181,
      "end_frame": 8219,
      "start": 4090.5,
      "end": 4110.0,
      "duration": 19.5,
      "original_video": "VmVxNRu4uIo",
      "original_segment_number": 44
    }
  ]
}